Workbook

Sheet 选品看板
A1: 闲鱼选品评级看板 · 产品编码表全量评估
A2: 数据源：产品编码.xlsx（7品牌 605 SKU）｜测算依据：闲鱼实时在售竞品价格分位、想要热度、竞争格局｜生成日期：2026-10-30
A3: 评估品类数 | C3: 可上架SKU数 | E3: S级爆款品类 | G3: A级铺货品类 | I3: 主推SKU占比
A4: =COUNTA(品类评级!B3:B106) -> 104 | C4: =COUNTA(SKU明细!B3:B607) -> 605 | E4: =COUNTIF(品类评级!C3:C106,"S") -> 1 | G4: =COUNTIF(品类评级!C3:C106,"A") -> 16 | I4: =IFERROR((COUNTIF(SKU明细!C3:C607,"S")+COUNTIF(SKU明细!C3:C607,"A"))/COUNTA(SKU明细!B3:B607),"") -> 0.11570248
A24: 评级 | B24: 品类数 | C24: SKU数 | D24: SKU占比 | F24: Top 12 优先铺货品类
A25: S | B25: =COUNTIF(品类评级!C3:C106,"S") -> 1 | C25: =COUNTIF(SKU明细!C3:C607,"S") -> 23 | D25: =IFERROR(C25/COUNTA(SKU明细!B3:B607),"") -> 0.038016529 | F25: 品类 | G25: 评级 | H25: 评分 | I25: 建议售价 | J25: 区间
A26: A | B26: =COUNTIF(品类评级!C3:C106,"A") -> 16 | C26: =COUNTIF(SKU明细!C3:C607,"A") -> 47 | D26: =IFERROR(C26/COUNTA(SKU明细!B3:B607),"") -> 0.07768595 | F26: 剃须刀刀头 | G26: S | H26: 8.17 | I26: 12 | J26: ¥9–15
A27: B | B27: =COUNTIF(品类评级!C3:C106,"B") -> 64 | C27: =COUNTIF(SKU明细!C3:C607,"B") -> 428 | D27: =IFERROR(C27/COUNTA(SKU明细!B3:B607),"") -> 0.70743802 | F27: 真空封口机 | G27: A | H27: 7.11 | I27: 26 | J27: ¥24–29
A28: C | B28: =COUNTIF(品类评级!C3:C106,"C") -> 22 | C28: =COUNTIF(SKU明细!C3:C607,"C") -> 103 | D28: =IFERROR(C28/COUNTA(SKU明细!B3:B607),"") -> 0.17024793 | F28: 高速吹风机 | G28: A | H28: 6.93 | I28: 55 | J28: ¥42–68
A29: D | B29: =COUNTIF(品类评级!C3:C106,"D") -> 1 | C29: =COUNTIF(SKU明细!C3:C607,"D") -> 4 | D29: =IFERROR(C29/COUNTA(SKU明细!B3:B607),"") -> 0.0066115702 | F29: 宠物修剪器 | G29: A | H29: 6.92 | I29: 18 | J29: ¥16–19
F30: 保暖口罩 | G30: A | H30: 6.87 | I30: 16 | J30: ¥15–16
F31: 手动刮胡刀 | G31: A | H31: 6.82 | I31: 24 | J31: ¥20–29
F32: 机油 | G32: A | H32: 6.8 | I32: 28 | J32: ¥17–40
F33: 迷你清洗杯 | G33: A | H33: 6.8 | I33: 2 | J33: ¥2–3
F34: 小气泡美容仪 | G34: A | H34: 6.79 | I34: 122 | J34: ¥105–139
F35: 防晒口罩 | G35: A | H35: 6.77 | I35: 14 | J35: ¥13–14
F36: 电动修眉刀 | G36: A | H36: 6.69 | I36: 12 | J36: ¥12–13
F37: 超声波清洗机 | G37: A | H37: 6.69 | I37: 50 | J37: ¥40–59

Sheet 品类评级
A1: 品类评级明细（评分 = 需求26% + 利润20% + 竞争16% + 售后14% + 合规10% + 新手9% + 复购5%，再按品牌力与合规红线调整）
A2: 序号 | B2: 品类 | C2: 评级 | D2: 综合评分 | E2: 竞品中位价 | F2: 建议售价 | G2: 建议区间 | H2: 最低可接受价 | I2: 竞品P25 | J2: 竞品P75 | K2: 想要中位 | L2: 在售样本 | M2: 全新占比 | N2: 需求 | O2: 利润 | P2: 竞争 | Q2: 售后 | R2: 合规 | S2: 新手 | T2: 复购 | U2: SKU数 | V2: 推荐理由 | W2: 行动建议
A3: 1 | B3: 剃须刀刀头 | C3: S | D3: 8.17 | E3: 15 | F3: 12 | G3: ¥9–15 | H3: 8 | I3: 11 | J3: 26 | K3: 113 | L3: 30 | M3: 0.6 | N3: 9.1 | O3: 5.5 | P3: 6.5 | Q3: 8 | R3: 10 | S3: 10 | T3: 10 | U3: =COUNTIF(SKU明细!D3:D607,B3) -> 23 | V3: 需求端表现突出：Top30 在售商品的「想要」人数中位数达 113，合计 8497 人次，说明该品类在闲鱼有稳定的自然搜索承接力；价格中等：全新竞品中位价 ¥15，主流带 ¥11–26，薄利走量，需控运损；竞争中等：Top30 中出现 5 个不同品牌，需要在主图和标题上做出差异；售后偏高：属电器/易损品类，需提前说明退换规则，建议保留开箱视频；⚠️ 合规强监管：属强资质敏感品类，资质/标签/宣称任一不合规即触发下架或扣分；耗材属性强：可与主机绑定做「主品+耗材」复购套餐，锁定回头客；新手友好：商品好描述、体积小发货轻、决策快，适合铺量上架 | W3: 全员力推，首批打满库存；标题带「全新未拆封+实拍」，主图放品牌背书
A4: 2 | B4: 真空封口机 | C4: A | D4: 7.11 | E4: 29 | F4: 26 | G4: ¥24–29 | H4: 15 | I4: 25 | J4: 35 | K4: 78 | L4: 30 | M4: 0.8 | N4: 8.5 | O4: 6.8 | P4: 6.2 | Q4: 3 | R4: 10 | S4: 8 | T4: 6 | U4: =COUNTIF(SKU明细!D3:D607,B4) -> 9 | V4: 需求端表现突出：Top30 在售商品的「想要」人数中位数达 78，合计 9156 人次，说明该品类在闲鱼有稳定的自然搜索承接力；价格中等：全新竞品中位价 ¥29，主流带 ¥25–35，薄利走量，需控运损；竞争中等：Top30 中出现 2 个不同品牌，需要在主图和标题上做出差异；售后风险极低：非电器或耗材形态，基本无充电/质保/退货纠纷；⚠️ 合规强监管：属强资质敏感品类，资质/标签/宣称任一不合规即触发下架或扣分；有一定复购：刀头/磨头/袋装等配套件可带动二次成交；该品类样本中未见自有品牌在售，属空白位——无内卷，但也需教育市场成本；新手友好：商品好描述、体积小发货轻、决策快，适合铺量上架 | W4: 重点铺货，建议配 3-5 个颜色SKU组套出图；可做「主推+搭售」组合
A5: 3 | B5: 高速吹风机 | C5: A | D5: 6.93 | E5: 68 | F5: 55 | G5: ¥42–68 | H5: 36 | I5: 42 | J5: 80 | K5: 41 | L5: 30 | M5: 0.77 | N5: 6.6 | O5: 8.5 | P5: 6.6 | Q5: 2 | R5: 9 | S5: 7 | T5: 6 | U5: =COUNTIF(SKU明细!D3:D607,B5) -> 2 | V5: 需求端表现突出：Top30 在售商品的「想要」人数中位数达 41，合计 7295 人次，说明该品类在闲鱼有稳定的自然搜索承接力；单件利润空间可观：全新竞品中位价 ¥68，P25–P75 主流带 ¥42–80，有腾挪定价空间；竞争中等：Top30 中出现 3 个不同品牌，需要在主图和标题上做出差异；售后风险极低：非电器或耗材形态，基本无充电/质保/退货纠纷；⚠️ 合规强监管：属强资质敏感品类，资质/标签/宣称任一不合规即触发下架或扣分；有一定复购：刀头/磨头/袋装等配套件可带动二次成交；该品类样本中未见自有品牌在售，属空白位——无内卷，但也需教育市场成本 | W5: 重点铺货，建议配 3-5 个颜色SKU组套出图；可做「主推+搭售」组合
A6: 4 | B6: 宠物修剪器 | C6: A | D6: 6.92 | E6: 19 | F6: 18 | G6: ¥16–19 | H6: 15 | I6: 17 | J6: 32 | K6: 156 | L6: 30 | M6: 0.77 | N6: 9.7 | O6: 6 | P6: 6.6 | Q6: 2 | R6: 10 | S6: 7 | T6: 5 | U6: =COUNTIF(SKU明细!D3:D607,B6) -> 1 | V6: 需求端表现突出：Top30 在售商品的「想要」人数中位数达 156，合计 3708 人次，说明该品类在闲鱼有稳定的自然搜索承接力；价格中等：全新竞品中位价 ¥19，主流带 ¥17–32，薄利走量，需控运损；竞争中等：Top30 中出现 0 个不同品牌，需要在主图和标题上做出差异；售后风险极低：非电器或耗材形态，基本无充电/质保/退货纠纷；⚠️ 合规强监管：属强资质敏感品类，资质/标签/宣称任一不合规即触发下架或扣分；有一定复购：刀头/磨头/袋装等配套件可带动二次成交；该品类样本中未见自有品牌在售，属空白位——无内卷，但也需教育市场成本 | W6: 重点铺货，建议配 3-5 个颜色SKU组套出图；可做「主推+搭售」组合
A7: 5 | B7: 保暖口罩 | C7: A | D7: 6.87 | E7: 16 | F7: 16 | G7: ¥15–16 | H7: 13 | I7: 15 | J7: 18 | K7: 112.5 | L7: 30 | M7: 0.77 | N7: 9.1 | O7: 5.7 | P7: 6.3 | Q7: 5 | R7: 5 | S7: 9 | T7: 7 | U7: =COUNTIF(SKU明细!D3:D607,B7) -> 3 | V7: 需求端表现突出：Top30 在售商品的「想要」人数中位数达 112，合计 8568 人次，说明该品类在闲鱼有稳定的自然搜索承接力；价格中等：全新竞品中位价 ¥16，主流带 ¥15–18，薄利走量，需控运损；竞争中等：Top30 中出现 1 个不同品牌，需要在主图和标题上做出差异；售后可控：常规小家电，做好成色描述与功能实测视频即可；宣称需克制：文案避免「治疗/根治/祛斑」等医疗功效词，用「清洁/护理/辅助」表述；有一定复购：刀头/磨头/袋装等配套件可带动二次成交；该品类样本中未见自有品牌在售，属空白位——无内卷，但也需教育市场成本；新手友好：商品好描述、体积小发货轻、决策快，适合铺量上架 | W7: 重点铺货，建议配 3-5 个颜色SKU组套出图；可做「主推+搭售」组合
A8: 6 | B8: 配件周边 | C8: D | D8: 6.85 | E8: 37 | F8: 20 | G8: ¥16–23 | H8: 15 | I8: 27 | J8: 56 | K8: 13 | L8: 30 | M8: 0.77 | N8: 4.6 | O8: 6.9 | P8: 5.6 | Q8: 9 | R8: 10 | S8: 9 | T8: 3 | U8: =COUNTIF(SKU明细!D3:D607,B8) -> 4 | V8: 需求极弱：「想要」人数中位数 13，几乎无自然流量承接；价格中等：全新竞品中位价 ¥37，主流带 ¥27–56，薄利走量，需控运损；竞争中等：Top30 中出现 9 个不同品牌，需要在主图和标题上做出差异；售后偏高：属电器/易损品类，需提前说明退换规则，建议保留开箱视频；⚠️ 合规强监管：非卖品配件/包装物，无独立售卖价值，资质/标签/宣称任一不合规即触发下架或扣分；🔥 自有品牌已在此品类跑通：Top30 竞品中有 5 条是康佳/奥克斯/夏新等自有品牌（占 17%），买家已有认知与搜索基础，上架即有流量基础，试错成本最低；新手友好：商品好描述、体积小发货轻、决策快，适合铺量上架 | W8: 不建议投入：合规/售后/需求三重风险，优先出库存或转做搭售赠品
A9: 7 | B9: 手动刮胡刀 | C9: A | D9: 6.82 | E9: 29 | F9: 24 | G9: ¥20–29 | H9: 9 | I9: 9 | J9: 35 | K9: 8 | L9: 30 | M9: 0.67 | N9: 4.7 | O9: 6.8 | P9: 6.4 | Q9: 7 | R9: 10 | S9: 9 | T9: 9 | U9: =COUNTIF(SKU明细!D3:D607,B9) -> 1 | V9: 需求端表现突出：Top30 在售商品的「想要」人数中位数达 8，合计 4279 人次，说明该品类在闲鱼有稳定的自然搜索承接力；价格中等：全新竞品中位价 ¥29，主流带 ¥9–35，薄利走量，需控运损；竞争中等：Top30 中出现 0 个不同品牌，需要在主图和标题上做出差异；售后可控：常规小家电，做好成色描述与功能实测视频即可；⚠️ 合规强监管：属强资质敏感品类，资质/标签/宣称任一不合规即触发下架或扣分；耗材属性强：可与主机绑定做「主品+耗材」复购套餐，锁定回头客；该品类样本中未见自有品牌在售，属空白位——无内卷，但也需教育市场成本；新手友好：商品好描述、体积小发货轻、决策快，适合铺量上架 | W9: 重点铺货，建议配 3-5 个颜色SKU组套出图；可做「主推+搭售」组合
A10: 8 | B10: 机油 | C10: A | D10: 6.8 | E10: 60 | F10: 28 | G10: ¥17–40 | H10: 16 | I10: 25 | J10: 65 | K10: 20 | L10: 30 | M10: 0.6 | N10: 5.3 | O10: 7.4 | P10: 6.7 | Q10: 7 | R10: 10 | S10: 8 | T10: 8 | U10: =COUNTIF(SKU明细!D3:D607,B10) -> 0 | V10: 需求端表现突出：Top30 在售商品的「想要」人数中位数达 20，合计 1221 人次，说明该品类在闲鱼有稳定的自然搜索承接力；单件利润空间可观：全新竞品中位价 ¥60，P25–P75 主流带 ¥25–65，有腾挪定价空间；竞争中等：Top30 中出现 0 个不同品牌，需要在主图和标题上做出差异；售后可控：常规小家电，做好成色描述与功能实测视频即可；⚠️ 合规强监管：属强资质敏感品类，资质/标签/宣称任一不合规即触发下架或扣分；耗材属性强：可与主机绑定做「主品+耗材」复购套餐，锁定回头客；该品类样本中未见自有品牌在售，属空白位——无内卷，但也需教育市场成本；新手友好：商品好描述、体积小发货轻、决策快，适合铺量上架 | W10: 重点铺货，建议配 3-5 个颜色SKU组套出图；可做「主推+搭售」组合
A11: 9 | B11: 迷你清洗杯 | C11: A | D11: 6.8 | E11: 3 | F11: 2 | G11: ¥2–3 | H11: 2 | I11: 2 | J11: 4 | K11: 78 | L11: 30 | M11: 0.33 | N11: 8.5 | O11: 2.8 | P11: 6.3 | Q11: 7 | R11: 10 | S11: 10 | T11: 8 | U11: =COUNTIF(SKU明细!D3:D607,B11) -> 1 | V11: 需求端表现突出：Top30 在售商品的「想要」人数中位数达 78，合计 8912 人次，说明该品类在闲鱼有稳定的自然搜索承接力；客单偏低：全新竞品中位价 ¥3，单件利润薄，必须靠走量或组合装摊薄运费；竞争中等：Top30 中出现 1 个不同品牌，需要在主图和标题上做出差异；售后可控：常规小家电，做好成色描述与功能实测视频即可；⚠️ 合规强监管：属强资质敏感品类，资质/标签/宣称任一不合规即触发下架或扣分；耗材属性强：可与主机绑定做「主品+耗材」复购套餐，锁定回头客；该品类样本中未见自有品牌在售，属空白位——无内卷，但也需教育市场成本；新手友好：商品好描述、体积小发货轻、决策快，适合铺量上架 | W11: 重点铺货，建议配 3-5 个颜色SKU组套出图；可做「主推+搭售」组合
A12: 10 | B12: 小气泡美容仪 | C12: A | D12: 6.79 | E12: 139 | F12: 122 | G12: ¥105–139 | H12: 93 | I12: 105 | J12: 150 | K12: 14 | L12: 30 | M12: 0 | N12: 5.5 | O12: 9.9 | P12: 6.6 | Q12: 4 | R12: 4 | S12: 7 | T12: 5 | U12: =COUNTIF(SKU明细!D3:D607,B12) -> 2 | V12: 需求端表现突出：Top30 在售商品的「想要」人数中位数达 14，合计 736 人次，说明该品类在闲鱼有稳定的自然搜索承接力；单件利润空间可观：全量竞品中位价 ¥139，P25–P75 主流带 ¥105–150，有腾挪定价空间；竞争中等：Top30 中出现 1 个不同品牌，需要在主图和标题上做出差异；售后风险极低：非电器或耗材形态，基本无充电/质保/退货纠纷；宣称需克制：文案避免「治疗/根治/祛斑」等医疗功效词，用「清洁/护理/辅助」表述；有一定复购：刀头/磨头/袋装等配套件可带动二次成交；自有品牌在该品类已有零星在售（2 条，占 7%），说明存在成交但尚未形成压倒性优势，适合抢占头部位置 | W12: 重点铺货，建议配 3-5 个颜色SKU组套出图；可做「主推+搭售」组合
A13: 11 | B13: 防晒口罩 | C13: A | D13: 6.77 | E13: 16 | F13: 14 | G13: ¥13–14 | H13: 8 | I13: 13 | J13: 19 | K13: 104.5 | L13: 30 | M13: 0.87 | N13: 9 | O13: 5.4 | P13: 6.2 | Q13: 5 | R13: 5 | S13: 9 | T13: 7 | U13: =COUNTIF(SKU明细!D3:D607,B13) -> 9 | V13: 需求端表现突出：Top30 在售商品的「想要」人数中位数达 104，合计 11322 人次，说明该品类在闲鱼有稳定的自然搜索承接力；价格中等：全新竞品中位价 ¥16，主流带 ¥13–19，薄利走量，需控运损；竞争中等：Top30 中出现 1 个不同品牌，需要在主图和标题上做出差异；售后可控：常规小家电，做好成色描述与功能实测视频即可；宣称需克制：文案避免「治疗/根治/祛斑」等医疗功效词，用「清洁/护理/辅助」表述；有一定复购：刀头/磨头/袋装等配套件可带动二次成交；该品类样本中未见自有品牌在售，属空白位——无内卷，但也需教育市场成本；新手友好：商品好描述、体积小发货轻、决策快，适合铺量上架 | W13: 重点铺货，建议配 3-5 个颜色SKU组套出图；可做「主推+搭售」组合
A14: 12 | B14: 电动修眉刀 | C14: A | D14: 6.69 | E14: 19 | F14: 12 | G14: ¥12–13 | H14: 10 | I14: 17 | J14: 58 | K14: 31 | L14: 30 | M14: 0.43 | N14: 6.1 | O14: 5.3 | P14: 6.8 | Q14: 3 | R14: 10 | S14: 9 | T14: 5 | U14: =COUNTIF(SKU明细!D3:D607,B14) -> 2 | V14: 需求端表现突出：Top30 在售商品的「想要」人数中位数达 31，合计 578 人次，说明该品类在闲鱼有稳定的自然搜索承接力；价格中等：全新竞品中位价 ¥19，主流带 ¥17–58，薄利走量，需控运损；竞争中等：Top30 中出现 3 个不同品牌，需要在主图和标题上做出差异；售后风险极低：非电器或耗材形态，基本无充电/质保/退货纠纷；⚠️ 合规强监管：属强资质敏感品类，资质/标签/宣称任一不合规即触发下架或扣分；有一定复购：刀头/磨头/袋装等配套件可带动二次成交；🔥 自有品牌已在此品类跑通：Top30 竞品中有 9 条是康佳/奥克斯/夏新等自有品牌（占 30%），买家已有认知与搜索基础，上架即有流量基础，试错成本最低；新手友好：商品好描述、体积小发货轻、决策快，适合铺量上架 | W14: 重点铺货，建议配 3-5 个颜色SKU组套出图；可做「主推+搭售」组合
A15: 13 | B15: 超声波清洗机 | C15: A | D15: 6.69 | E15: 59 | F15: 50 | G15: ¥40–59 | H15: 18 | I15: 41 | J15: 90 | K15: 12 | L15: 30 | M15: 0.4 | N15: 4.5 | O15: 8.2 | P15: 6.8 | Q15: 4 | R15: 8 | S15: 8 | T15: 7 | U15: =COUNTIF(SKU明细!D3:D607,B15) -> 1 | V15: 需求端表现突出：Top30 在售商品的「想要」人数中位数达 12，合计 8476 人次，说明该品类在闲鱼有稳定的自然搜索承接力；单件利润空间可观：全新竞品中位价 ¥59，P25–P75 主流带 ¥41–90，有腾挪定价空间；竞争中等：Top30 中出现 4 个不同品牌，需要在主图和标题上做出差异；售后风险极低：非电器或耗材形态，基本无充电/质保/退货纠纷；⚠️ 合规强监管：属强资质敏感品类，资质/标签/宣称任一不合规即触发下架或扣分；有一定复购：刀头/磨头/袋装等配套件可带动二次成交；新手友好：商品好描述、体积小发货轻、决策快，适合铺量上架 | W15: 重点铺货，建议配 3-5 个颜色SKU组套出图；可做「主推+搭售」组合
A16: 14 | B16: 马桶卫士 | C16: A | D16: 6.68 | E16: 13 | F16: 12 | G16: ¥12–13 | H16: 7 | I16: 9 | J16: 17 | K16: 50 | L16: 30 | M16: 0.4 | N16: 7.7 | O16: 5.3 | P16: 6.4 | Q16: 6 | R16: 8 | S16: 9 | T16: 8 | U16: =COUNTIF(SKU明细!D3:D607,B16) -> 3 | V16: 需求端表现突出：Top30 在售商品的「想要」人数中位数达 50，合计 2258 人次，说明该品类在闲鱼有稳定的自然搜索承接力；价格中等：全新竞品中位价 ¥13，主流带 ¥9–17，薄利走量，需控运损；竞争中等：Top30 中出现 0 个不同品牌，需要在主图和标题上做出差异；售后可控：常规小家电，做好成色描述与功能实测视频即可；⚠️ 合规强监管：属强资质敏感品类，资质/标签/宣称任一不合规即触发下架或扣分；耗材属性强：可与主机绑定做「主品+耗材」复购套餐，锁定回头客；该品类样本中未见自有品牌在售，属空白位——无内卷，但也需教育市场成本；新手友好：商品好描述、体积小发货轻、决策快，适合铺量上架 | W16: 重点铺货，建议配 3-5 个颜色SKU组套出图；可做「主推+搭售」组合
A17: 15 | B17: 起泡网 | C17: A | D17: 6.66 | E17: 9 | F17: 8 | G17: ¥7–9 | H17: 6 | I17: 4 | J17: 9 | K17: 20 | L17: 30 | M17: 0.47 | N17: 6.1 | O17: 4.6 | P17: 6.5 | Q17: 8 | R17: 10 | S17: 10 | T17: 9 | U17: =COUNTIF(SKU明细!D3:D607,B17) -> 1 | V17: 需求端表现突出：Top30 在售商品的「想要」人数中位数达 20，合计 960 人次，说明该品类在闲鱼有稳定的自然搜索承接力；客单偏低：全新竞品中位价 ¥9，单件利润薄，必须靠走量或组合装摊薄运费；竞争中等：Top30 中出现 0 个不同品牌，需要在主图和标题上做出差异；售后偏高：属电器/易损品类，需提前说明退换规则，建议保留开箱视频；⚠️ 合规强监管：属强资质敏感品类，资质/标签/宣称任一不合规即触发下架或扣分；耗材属性强：可与主机绑定做「主品+耗材」复购套餐，锁定回头客；该品类样本中未见自有品牌在售，属空白位——无内卷，但也需教育市场成本；新手友好：商品好描述、体积小发货轻、决策快，适合铺量上架 | W17: 重点铺货，建议配 3-5 个颜色SKU组套出图；可做「主推+搭售」组合
A18: 16 | B18: 挂腰风扇 | C18: A | D18: 6.65 | E18: 49 | F18: 44 | G18: ¥38–49 | H18: 36 | I18: 38 | J18: 65 | K18: 16 | L18: 30 | M18: 0.47 | N18: 5.8 | O18: 7.8 | P18: 6.4 | Q18: 4 | R18: 10 | S18: 8 | T18: 3 | U18: =COUNTIF(SKU明细!D3:D607,B18) -> 3 | V18: 需求端表现突出：Top30 在售商品的「想要」人数中位数达 16，合计 2412 人次，说明该品类在闲鱼有稳定的自然搜索承接力；单件利润空间可观：全新竞品中位价 ¥49，P25–P75 主流带 ¥38–65，有腾挪定价空间；竞争中等：Top30 中出现 1 个不同品牌，需要在主图和标题上做出差异；售后风险极低：非电器或耗材形态，基本无充电/质保/退货纠纷；⚠️ 合规强监管：属强资质敏感品类，资质/标签/宣称任一不合规即触发下架或扣分；自有品牌在该品类已有零星在售（2 条，占 7%），说明存在成交但尚未形成压倒性优势，适合抢占头部位置；新手友好：商品好描述、体积小发货轻、决策快，适合铺量上架 | W18: 重点铺货，建议配 3-5 个颜色SKU组套出图；可做「主推+搭售」组合
A19: 17 | B19: 循环扇 | C19: A | D19: 6.63 | E19: 24 | F19: 22 | G19: ¥21–24 | H19: 18 | I19: 21 | J19: 25 | K19: 76.5 | L19: 30 | M19: 0.87 | N19: 8.4 | O19: 6.4 | P19: 6.4 | Q19: 2 | R19: 9 | S19: 7 | T19: 4 | U19: =COUNTIF(SKU明细!D3:D607,B19) -> 2 | V19: 需求端表现突出：Top30 在售商品的「想要」人数中位数达 76，合计 24235 人次，说明该品类在闲鱼有稳定的自然搜索承接力；价格中等：全新竞品中位价 ¥24，主流带 ¥21–25，薄利走量，需控运损；竞争中等：Top30 中出现 1 个不同品牌，需要在主图和标题上做出差异；售后风险极低：非电器或耗材形态，基本无充电/质保/退货纠纷；⚠️ 合规强监管：属强资质敏感品类，资质/标签/宣称任一不合规即触发下架或扣分；该品类样本中未见自有品牌在售，属空白位——无内卷，但也需教育市场成本 | W19: 重点铺货，建议配 3-5 个颜色SKU组套出图；可做「主推+搭售」组合
A20: 18 | B20: 自动卷发器 | C20: A | D20: 6.63 | E20: 30 | F20: 25 | G20: ¥20–30 | H20: 18 | I20: 23 | J20: 35 | K20: 59 | L20: 30 | M20: 0.57 | N20: 7.2 | O20: 6.9 | P20: 6.9 | Q20: 1 | R20: 9 | S20: 7 | T20: 5 | U20: =COUNTIF(SKU明细!D3:D607,B20) -> 7 | V20: 需求端表现突出：Top30 在售商品的「想要」人数中位数达 59，合计 4533 人次，说明该品类在闲鱼有稳定的自然搜索承接力；价格中等：全新竞品中位价 ¥30，主流带 ¥23–35，薄利走量，需控运损；竞争中等：Top30 中出现 2 个不同品牌，需要在主图和标题上做出差异；售后风险极低：非电器或耗材形态，基本无充电/质保/退货纠纷；⚠️ 合规强监管：属强资质敏感品类，资质/标签/宣称任一不合规即触发下架或扣分；有一定复购：刀头/磨头/袋装等配套件可带动二次成交；自有品牌在该品类已有零星在售（2 条，占 7%），说明存在成交但尚未形成压倒性优势，适合抢占头部位置 | W20: 重点铺货，建议配 3-5 个颜色SKU组套出图；可做「主推+搭售」组合
A21: 19 | B21: 破壁料理机 | C21: B | D21: 6.6 | E21: 59 | F21: 38 | G21: ¥38–39 | H21: 36 | I21: 44 | J21: 69 | K21: 14 | L21: 30 | M21: 0.33 | N21: 5.5 | O21: 8.1 | P21: 6.6 | Q21: 1 | R21: 9 | S21: 5 | T21: 5 | U21: =COUNTIF(SKU明细!D3:D607,B21) -> 2 | V21: 需求中等：「想要」人数中位数 14、有想要标签的在售占比 16/30，属于有搜索但竞争平缓的常规位；单件利润空间可观：全新竞品中位价 ¥59，P25–P75 主流带 ¥44–69，有腾挪定价空间；竞争中等：Top30 中出现 6 个不同品牌，需要在主图和标题上做出差异；售后风险极低：非电器或耗材形态，基本无充电/质保/退货纠纷；⚠️ 合规强监管：属强资质敏感品类，资质/标签/宣称任一不合规即触发下架或扣分；有一定复购：刀头/磨头/袋装等配套件可带动二次成交；🔥 自有品牌已在此品类跑通：Top30 竞品中有 5 条是康佳/奥克斯/夏新等自有品牌（占 17%），买家已有认知与搜索基础，上架即有流量基础，试错成本最低；新手门槛偏高：需讲清参数/尺寸/安装或操作说明，图文投入要足 | W21: 常规备选，放在长尾分类；用低价冲量，不单独投流
A22: 20 | B22: 除螨皂 | C22: B | D22: 6.59 | E22: 15 | F22: 8 | G22: ¥6–11 | H22: 6 | I22: 9 | J22: 24 | K22: 92.5 | L22: 30 | M22: 0.47 | N22: 8.8 | O22: 5.5 | P22: 6.6 | Q22: 5 | R22: 2 | S22: 9 | T22: 9 | U22: =COUNTIF(SKU明细!D3:D607,B22) -> 1 | V22: 需求中等：「想要」人数中位数 92、有想要标签的在售占比 16/30，属于有搜索但竞争平缓的常规位；价格中等：全新竞品中位价 ¥15，主流带 ¥9–24，薄利走量，需控运损；竞争中等：Top30 中出现 1 个不同品牌，需要在主图和标题上做出差异；售后可控：常规小家电，做好成色描述与功能实测视频即可；无资质门槛：上架无特殊资质要求，标题可自由发挥；耗材属性强：可与主机绑定做「主品+耗材」复购套餐，锁定回头客；该品类样本中未见自有品牌在售，属空白位——无内卷，但也需教育市场成本；新手友好：商品好描述、体积小发货轻、决策快，适合铺量上架 | W22: 常规备选，放在长尾分类；用低价冲量，不单独投流
A23: 21 | B23: 修足器磨头 | C23: B | D23: 6.54 | E23: 30 | F23: 14 | G23: ¥10–17 | H23: 10 | I23: 18 | J23: 43 | K23: 1 | L23: 30 | M23: 0.73 | N23: 1.2 | O23: 6.8 | P23: 6.8 | Q23: 8 | R23: 10 | S23: 10 | T23: 10 | U23: =COUNTIF(SKU明细!D3:D607,B23) -> 6 | V23: 需求中等：「想要」人数中位数 1、有想要标签的在售占比 10/30，属于有搜索但竞争平缓的常规位；价格中等：全新竞品中位价 ¥30，主流带 ¥18–43，薄利走量，需控运损；竞争中等：Top30 中出现 4 个不同品牌，需要在主图和标题上做出差异；售后偏高：属电器/易损品类，需提前说明退换规则，建议保留开箱视频；⚠️ 合规强监管：属强资质敏感品类，资质/标签/宣称任一不合规即触发下架或扣分；耗材属性强：可与主机绑定做「主品+耗材」复购套餐，锁定回头客；🔥 自有品牌已在此品类跑通：Top30 竞品中有 9 条是康佳/奥克斯/夏新等自有品牌（占 30%），买家已有认知与搜索基础，上架即有流量基础，试错成本最低；新手友好：商品好描述、体积小发货轻、决策快，适合铺量上架 | W23: 常规备选，放在长尾分类；用低价冲量，不单独投流
A24: 22 | B24: 车载吸尘器 | C24: B | D24: 6.5 | E24: 39 | F24: 26 | G24: ¥24–29 | H24: 23 | I24: 32 | J24: 48 | K24: 18.5 | L24: 30 | M24: 0.8 | N24: 6 | O24: 7.4 | P24: 6.5 | Q24: 2 | R24: 9 | S24: 7 | T24: 5 | U24: =COUNTIF(SKU明细!D3:D607,B24) -> 14 | V24: 需求中等：「想要」人数中位数 18、有想要标签的在售占比 18/30，属于有搜索但竞争平缓的常规位；单件利润空间可观：全新竞品中位价 ¥39，P25–P75 主流带 ¥32–48，有腾挪定价空间；竞争中等：Top30 中出现 4 个不同品牌，需要在主图和标题上做出差异；售后风险极低：非电器或耗材形态，基本无充电/质保/退货纠纷；⚠️ 合规强监管：属强资质敏感品类，资质/标签/宣称任一不合规即触发下架或扣分；有一定复购：刀头/磨头/袋装等配套件可带动二次成交 | W24: 常规备选，放在长尾分类；用低价冲量，不单独投流
A25: 23 | B25: 采耳耳勺可视 | C25: B | D25: 6.45 | E25: 23 | F25: 15 | G25: ¥15–15 | H25: 14 | I25: 15 | J25: 69 | K25: 53 | L25: 30 | M25: 0.73 | N25: 7 | O25: 6.3 | P25: 6.7 | Q25: 3 | R25: 10 | S25: 8 | T25: 3 | U25: =COUNTIF(SKU明细!D3:D607,B25) -> 2 | V25: 需求中等：「想要」人数中位数 53、有想要标签的在售占比 13/30，属于有搜索但竞争平缓的常规位；价格中等：全新竞品中位价 ¥23，主流带 ¥15–69，薄利走量，需控运损；竞争中等：Top30 中出现 1 个不同品牌，需要在主图和标题上做出差异；售后风险极低：非电器或耗材形态，基本无充电/质保/退货纠纷；⚠️ 合规强监管：属强资质敏感品类，资质/标签/宣称任一不合规即触发下架或扣分；该品类样本中未见自有品牌在售，属空白位——无内卷，但也需教育市场成本；新手友好：商品好描述、体积小发货轻、决策快，适合铺量上架 | W25: 常规备选，放在长尾分类；用低价冲量，不单独投流
A26: 24 | B26: 电动磨甲器 | C26: B | D26: 6.42 | E26: 23 | F26: 14 | G26: ¥13–16 | H26: 12 | I26: 15 | J26: 27 | K26: 102 | L26: 60 | M26: 0.7 | N26: 8.9 | O26: 6.3 | P26: 3.6 | Q26: 2 | R26: 10 | S26: 8 | T26: 5 | U26: =COUNTIF(SKU明细!D3:D607,B26) -> 2 | V26: 需求中等：「想要」人数中位数 102、有想要标签的在售占比 19/30，属于有搜索但竞争平缓的常规位；价格中等：全新竞品中位价 ¥23，主流带 ¥15–27，薄利走量，需控运损；竞争激烈：Top30 里已挤进 0 个品牌，头部品牌已形成价格锚定，正面硬拼不划算；售后风险极低：非电器或耗材形态，基本无充电/质保/退货纠纷；⚠️ 合规强监管：属强资质敏感品类，资质/标签/宣称任一不合规即触发下架或扣分；有一定复购：刀头/磨头/袋装等配套件可带动二次成交；该品类样本中未见自有品牌在售，属空白位——无内卷，但也需教育市场成本；新手友好：商品好描述、体积小发货轻、决策快，适合铺量上架 | W26: 常规备选，放在长尾分类；用低价冲量，不单独投流
A27: 25 | B27: 肩颈按摩器 | C27: B | D27: 6.42 | E27: 35 | F27: 22 | G27: ¥17–28 | H27: 16 | I27: 28 | J27: 51 | K27: 18 | L27: 30 | M27: 0.53 | N27: 5.2 | O27: 7.2 | P27: 6.8 | Q27: 3 | R27: 7 | S27: 7 | T27: 4 | U27: =COUNTIF(SKU明细!D3:D607,B27) -> 10 | V27: 需求中等：「想要」人数中位数 18、有想要标签的在售占比 11/30，属于有搜索但竞争平缓的常规位；单件利润空间可观：全新竞品中位价 ¥35，P25–P75 主流带 ¥28–51，有腾挪定价空间；竞争中等：Top30 中出现 2 个不同品牌，需要在主图和标题上做出差异；售后风险极低：非电器或耗材形态，基本无充电/质保/退货纠纷；⚠️ 合规强监管：属强资质敏感品类，资质/标签/宣称任一不合规即触发下架或扣分；🔥 自有品牌已在此品类跑通：Top30 竞品中有 17 条是康佳/奥克斯/夏新等自有品牌（占 57%），买家已有认知与搜索基础，上架即有流量基础，试错成本最低 | W27: 常规备选，放在长尾分类；用低价冲量，不单独投流
A28: 26 | B28: 烘鞋器 | C28: B | D28: 6.41 | E28: 19 | F28: 14 | G28: ¥11–16 | H28: 10 | I28: 16 | J28: 28 | K28: 26 | L28: 30 | M28: 0.8 | N28: 6.6 | O28: 6 | P28: 6.6 | Q28: 2 | R28: 10 | S28: 8 | T28: 4 | U28: =COUNTIF(SKU明细!D3:D607,B28) -> 2 | V28: 需求中等：「想要」人数中位数 26、有想要标签的在售占比 15/30，属于有搜索但竞争平缓的常规位；价格中等：全新竞品中位价 ¥19，主流带 ¥16–28，薄利走量，需控运损；竞争中等：Top30 中出现 4 个不同品牌，需要在主图和标题上做出差异；售后风险极低：非电器或耗材形态，基本无充电/质保/退货纠纷；⚠️ 合规强监管：属强资质敏感品类，资质/标签/宣称任一不合规即触发下架或扣分；自有品牌在该品类已有零星在售（2 条，占 7%），说明存在成交但尚未形成压倒性优势，适合抢占头部位置；新手友好：商品好描述、体积小发货轻、决策快，适合铺量上架 | W28: 常规备选，放在长尾分类；用低价冲量，不单独投流
A29: 27 | B29: 咖啡豆研磨机 | C29: B | D29: 6.37 | E29: 39 | F29: 18 | G29: ¥14–23 | H29: 13 | I29: 20 | J29: 60 | K29: 16.5 | L29: 30 | M29: 0.73 | N29: 5 | O29: 7.2 | P29: 6.6 | Q29: 3 | R29: 10 | S29: 8 | T29: 6 | U29: =COUNTIF(SKU明细!D3:D607,B29) -> 1 | V29: 需求中等：「想要」人数中位数 16、有想要标签的在售占比 14/30，属于有搜索但竞争平缓的常规位；单件利润空间可观：全新竞品中位价 ¥39，P25–P75 主流带 ¥20–60，有腾挪定价空间；竞争中等：Top30 中出现 4 个不同品牌，需要在主图和标题上做出差异；售后风险极低：非电器或耗材形态，基本无充电/质保/退货纠纷；⚠️ 合规强监管：属强资质敏感品类，资质/标签/宣称任一不合规即触发下架或扣分；有一定复购：刀头/磨头/袋装等配套件可带动二次成交；该品类样本中未见自有品牌在售，属空白位——无内卷，但也需教育市场成本；新手友好：商品好描述、体积小发货轻、决策快，适合铺量上架 | W29: 常规备选，放在长尾分类；用低价冲量，不单独投流
A30: 28 | B30: 直发器 | C30: B | D30: 6.37 | E30: 35 | F30: 17 | G30: ¥15–19 | H30: 14 | I30: 19 | J30: 49 | K30: 4 | L30: 30 | M30: 0.63 | N30: 3.6 | O30: 7.2 | P30: 6.6 | Q30: 2 | R30: 9 | S30: 8 | T30: 6 | U30: =COUNTIF(SKU明细!D3:D607,B30) -> 8 | V30: 需求中等：「想要」人数中位数 4、有想要标签的在售占比 15/30，属于有搜索但竞争平缓的常规位；单件利润空间可观：全新竞品中位价 ¥35，P25–P75 主流带 ¥19–49，有腾挪定价空间；竞争中等：Top30 中出现 4 个不同品牌，需要在主图和标题上做出差异；售后风险极低：非电器或耗材形态，基本无充电/质保/退货纠纷；⚠️ 合规强监管：属强资质敏感品类，资质/标签/宣称任一不合规即触发下架或扣分；有一定复购：刀头/磨头/袋装等配套件可带动二次成交；🔥 自有品牌已在此品类跑通：Top30 竞品中有 5 条是康佳/奥克斯/夏新等自有品牌（占 17%），买家已有认知与搜索基础，上架即有流量基础，试错成本最低；新手友好：商品好描述、体积小发货轻、决策快，适合铺量上架 | W30: 常规备选，放在长尾分类；用低价冲量，不单独投流
A31: 29 | B31: 美容仪 | C31: B | D31: 6.36 | E31: 346 | F31: 289 | G31: ¥280–298 | H31: 266 | I31: 280 | J31: 426 | K31: 26.5 | L31: 30 | M31: 0.67 | N31: 5.8 | O31: 10 | P31: 7 | Q31: 4 | R31: 2 | S31: 6 | T31: 4 | U31: =COUNTIF(SKU明细!D3:D607,B31) -> 7 | V31: 需求中等：「想要」人数中位数 26、有想要标签的在售占比 6/30，属于有搜索但竞争平缓的常规位；单件利润空间可观：全新竞品中位价 ¥346，P25–P75 主流带 ¥280–426，有腾挪定价空间；竞争温和：在售 Top30 覆盖 1 个品牌，格局分散，新链接有出头机会；售后风险极低：非电器或耗材形态，基本无充电/质保/退货纠纷；无资质门槛：上架无特殊资质要求，标题可自由发挥；该品类样本中未见自有品牌在售，属空白位——无内卷，但也需教育市场成本 | W31: 常规备选，放在长尾分类；用低价冲量，不单独投流
A32: 30 | B32: 吹风机 | C32: B | D32: 6.34 | E32: 43 | F32: 26 | G32: ¥15–37 | H32: 14 | I32: 35 | J32: 68 | K32: 48 | L32: 60 | M32: 0.68 | N32: 7.6 | O32: 7.5 | P32: 3.2 | Q32: 2 | R32: 9 | S32: 7 | T32: 6 | U32: =COUNTIF(SKU明细!D3:D607,B32) -> 3 | V32: 需求中等：「想要」人数中位数 48、有想要标签的在售占比 31/30，属于有搜索但竞争平缓的常规位；单件利润空间可观：全新竞品中位价 ¥43，P25–P75 主流带 ¥35–68，有腾挪定价空间；竞争激烈：Top30 里已挤进 6 个品牌，头部品牌已形成价格锚定，正面硬拼不划算；售后风险极低：非电器或耗材形态，基本无充电/质保/退货纠纷；⚠️ 合规强监管：属强资质敏感品类，资质/标签/宣称任一不合规即触发下架或扣分；有一定复购：刀头/磨头/袋装等配套件可带动二次成交；该品类样本中未见自有品牌在售，属空白位——无内卷，但也需教育市场成本 | W32: 常规备选，放在长尾分类；用低价冲量，不单独投流
A33: 31 | B33: 冲牙器 | C33: B | D33: 6.31 | E33: 41 | F33: 20 | G33: ¥20–20 | H33: 19 | I33: 25 | J33: 42 | K33: 3.5 | L33: 30 | M33: 0.47 | N33: 2.6 | O33: 7 | P33: 6.8 | Q33: 3 | R33: 10 | S33: 7 | T33: 7 | U33: =COUNTIF(SKU明细!D3:D607,B33) -> 9 | V33: 需求中等：「想要」人数中位数 4、有想要标签的在售占比 10/30，属于有搜索但竞争平缓的常规位；单件利润空间可观：全新竞品中位价 ¥41，P25–P75 主流带 ¥25–42，有腾挪定价空间；竞争中等：Top30 中出现 3 个不同品牌，需要在主图和标题上做出差异；售后风险极低：非电器或耗材形态，基本无充电/质保/退货纠纷；⚠️ 合规强监管：属强资质敏感品类，资质/标签/宣称任一不合规即触发下架或扣分；有一定复购：刀头/磨头/袋装等配套件可带动二次成交；🔥 自有品牌已在此品类跑通：Top30 竞品中有 12 条是康佳/奥克斯/夏新等自有品牌（占 40%），买家已有认知与搜索基础，上架即有流量基础，试错成本最低 | W33: 常规备选，放在长尾分类；用低价冲量，不单独投流
A34: 32 | B34: 多功能研磨机 | C34: B | D34: 6.31 | E34: 25 | F34: 19 | G34: ¥19–19 | H34: 18 | I34: 19 | J34: 27 | K34: 18 | L34: 30 | M34: 0.77 | N34: 6 | O34: 6.5 | P34: 6.4 | Q34: 3 | R34: 10 | S34: 8 | T34: 6 | U34: =COUNTIF(SKU明细!D3:D607,B34) -> 3 | V34: 需求中等：「想要」人数中位数 18、有想要标签的在售占比 20/30，属于有搜索但竞争平缓的常规位；价格中等：全新竞品中位价 ¥25，主流带 ¥19–27，薄利走量，需控运损；竞争中等：Top30 中出现 0 个不同品牌，需要在主图和标题上做出差异；售后风险极低：非电器或耗材形态，基本无充电/质保/退货纠纷；⚠️ 合规强监管：属强资质敏感品类，资质/标签/宣称任一不合规即触发下架或扣分；有一定复购：刀头/磨头/袋装等配套件可带动二次成交；该品类样本中未见自有品牌在售，属空白位——无内卷，但也需教育市场成本；新手友好：商品好描述、体积小发货轻、决策快，适合铺量上架 | W34: 常规备选，放在长尾分类；用低价冲量，不单独投流
A35: 33 | B35: 洗手液 | C35: B | D35: 6.31 | E35: 7 | F35: 4 | G35: ¥3–5 | H35: 3 | I35: 6 | J35: 13 | K35: 113.5 | L35: 30 | M35: 0.6 | N35: 9.1 | O35: 4.2 | P35: 6.6 | Q35: 5 | R35: 1 | S35: 9 | T35: 9 | U35: =COUNTIF(SKU明细!D3:D607,B35) -> 0 | V35: 需求中等：「想要」人数中位数 114、有想要标签的在售占比 16/30，属于有搜索但竞争平缓的常规位；客单偏低：全新竞品中位价 ¥7，单件利润薄，必须靠走量或组合装摊薄运费；竞争中等：Top30 中出现 0 个不同品牌，需要在主图和标题上做出差异；售后可控：常规小家电，做好成色描述与功能实测视频即可；无资质门槛：上架无特殊资质要求，标题可自由发挥；耗材属性强：可与主机绑定做「主品+耗材」复购套餐，锁定回头客；该品类样本中未见自有品牌在售，属空白位——无内卷，但也需教育市场成本；新手友好：商品好描述、体积小发货轻、决策快，适合铺量上架 | W35: 常规备选，放在长尾分类；用低价冲量，不单独投流
A36: 34 | B36: 电动磨脚器 | C36: B | D36: 6.31 | E36: 29 | F36: 18 | G36: ¥12–24 | H36: 11 | I36: 19 | J36: 36 | K36: 9.5 | L36: 30 | M36: 0.83 | N36: 4.1 | O36: 6.8 | P36: 6.6 | Q36: 2 | R36: 10 | S36: 8 | T36: 4 | U36: =COUNTIF(SKU明细!D3:D607,B36) -> 25 | V36: 需求中等：「想要」人数中位数 10、有想要标签的在售占比 14/30，属于有搜索但竞争平缓的常规位；价格中等：全新竞品中位价 ¥29，主流带 ¥19–36，薄利走量，需控运损；竞争中等：Top30 中出现 3 个不同品牌，需要在主图和标题上做出差异；售后风险极低：非电器或耗材形态，基本无充电/质保/退货纠纷；⚠️ 合规强监管：属强资质敏感品类，资质/标签/宣称任一不合规即触发下架或扣分；🔥 自有品牌已在此品类跑通：Top30 竞品中有 9 条是康佳/奥克斯/夏新等自有品牌（占 30%），买家已有认知与搜索基础，上架即有流量基础，试错成本最低；新手友好：商品好描述、体积小发货轻、决策快，适合铺量上架 | W36: 常规备选，放在长尾分类；用低价冲量，不单独投流
A37: 35 | B37: 鼻毛修剪器刀头 | C37: B | D37: 6.25 | E37: 15 | F37: 4 | G37: ¥4–5 | H37: 4 | I37: 6 | J37: 18 | K37: 5 | L37: 30 | M37: 0.43 | N37: 3.9 | O37: 4.6 | P37: 6.4 | Q37: 8 | R37: 10 | S37: 10 | T37: 10 | U37: =COUNTIF(SKU明细!D3:D607,B37) -> 0 | V37: 需求中等：「想要」人数中位数 5、有想要标签的在售占比 19/30，属于有搜索但竞争平缓的常规位；客单偏低：全新竞品中位价 ¥15，单件利润薄，必须靠走量或组合装摊薄运费；竞争中等：Top30 中出现 5 个不同品牌，需要在主图和标题上做出差异；售后偏高：属电器/易损品类，需提前说明退换规则，建议保留开箱视频；⚠️ 合规强监管：属强资质敏感品类，资质/标签/宣称任一不合规即触发下架或扣分；耗材属性强：可与主机绑定做「主品+耗材」复购套餐，锁定回头客；该品类样本中未见自有品牌在售，属空白位——无内卷，但也需教育市场成本；新手友好：商品好描述、体积小发货轻、决策快，适合铺量上架 | W37: 常规备选，放在长尾分类；用低价冲量，不单独投流
A38: 36 | B38: 粘毛器 | C38: B | D38: 6.22 | E38: 6 | F38: 4 | G38: ¥3–4 | H38: 3 | I38: 3 | J38: 9 | K38: 10.5 | L38: 30 | M38: 0.8 | N38: 5.1 | O38: 3.9 | P38: 6.5 | Q38: 7 | R38: 10 | S38: 10 | T38: 9 | U38: =COUNTIF(SKU明细!D3:D607,B38) -> 0 | V38: 需求中等：「想要」人数中位数 10、有想要标签的在售占比 18/30，属于有搜索但竞争平缓的常规位；客单偏低：全新竞品中位价 ¥6，单件利润薄，必须靠走量或组合装摊薄运费；竞争中等：Top30 中出现 1 个不同品牌，需要在主图和标题上做出差异；售后可控：常规小家电，做好成色描述与功能实测视频即可；⚠️ 合规强监管：属强资质敏感品类，资质/标签/宣称任一不合规即触发下架或扣分；耗材属性强：可与主机绑定做「主品+耗材」复购套餐，锁定回头客；该品类样本中未见自有品牌在售，属空白位——无内卷，但也需教育市场成本；新手友好：商品好描述、体积小发货轻、决策快，适合铺量上架 | W38: 常规备选，放在长尾分类；用低价冲量，不单独投流
A39: 37 | B39: 呼吸哑铃 | C39: B | D39: 6.21 | E39: 80 | F39: 54 | G39: ¥48–59 | H39: 46 | I39: 59 | J39: 108 | K39: 2 | L39: 30 | M39: 0.77 | N39: 1.9 | O39: 8.8 | P39: 6.9 | Q39: 7 | R39: 10 | S39: 9 | T39: 6 | U39: =COUNTIF(SKU明细!D3:D607,B39) -> 1 | V39: 需求中等：「想要」人数中位数 2、有想要标签的在售占比 7/30，属于有搜索但竞争平缓的常规位；单件利润空间可观：全新竞品中位价 ¥80，P25–P75 主流带 ¥59–108，有腾挪定价空间；竞争中等：Top30 中出现 0 个不同品牌，需要在主图和标题上做出差异；售后可控：常规小家电，做好成色描述与功能实测视频即可；⚠️ 合规强监管：属强资质敏感品类，资质/标签/宣称任一不合规即触发下架或扣分；有一定复购：刀头/磨头/袋装等配套件可带动二次成交；该品类样本中未见自有品牌在售，属空白位——无内卷，但也需教育市场成本；新手友好：商品好描述、体积小发货轻、决策快，适合铺量上架 | W39: 常规备选，放在长尾分类；用低价冲量，不单独投流
A40: 38 | B40: 洗衣杯 | C40: B | D40: 6.2 | E40: 53 | F40: 30 | G40: ¥25–36 | H40: 24 | I40: 39 | J40: 65 | K40: 2.5 | L40: 30 | M40: 0.5 | N40: 2.2 | O40: 8 | P40: 6.7 | Q40: 6 | R40: 10 | S40: 9 | T40: 6 | U40: =COUNTIF(SKU明细!D3:D607,B40) -> 1 | V40: 需求中等：「想要」人数中位数 2、有想要标签的在售占比 12/30，属于有搜索但竞争平缓的常规位；单件利润空间可观：全新竞品中位价 ¥53，P25–P75 主流带 ¥39–65，有腾挪定价空间；竞争中等：Top30 中出现 1 个不同品牌，需要在主图和标题上做出差异；售后可控：常规小家电，做好成色描述与功能实测视频即可；⚠️ 合规强监管：属强资质敏感品类，资质/标签/宣称任一不合规即触发下架或扣分；有一定复购：刀头/磨头/袋装等配套件可带动二次成交；自有品牌在该品类已有零星在售（2 条，占 7%），说明存在成交但尚未形成压倒性优势，适合抢占头部位置；新手友好：商品好描述、体积小发货轻、决策快，适合铺量上架 | W40: 常规备选，放在长尾分类；用低价冲量，不单独投流
A41: 39 | B41: 直发梳 | C41: B | D41: 6.2 | E41: 49 | F41: 28 | G41: ¥20–35 | H41: 19 | I41: 35 | J41: 53 | K41: 8 | L41: 30 | M41: 0.5 | N41: 3.9 | O41: 7.8 | P41: 6.7 | Q41: 2 | R41: 9 | S41: 8 | T41: 6 | U41: =COUNTIF(SKU明细!D3:D607,B41) -> 25 | V41: 需求中等：「想要」人数中位数 8、有想要标签的在售占比 13/30，属于有搜索但竞争平缓的常规位；单件利润空间可观：全新竞品中位价 ¥49，P25–P75 主流带 ¥35–53，有腾挪定价空间；竞争中等：Top30 中出现 2 个不同品牌，需要在主图和标题上做出差异；售后风险极低：非电器或耗材形态，基本无充电/质保/退货纠纷；⚠️ 合规强监管：属强资质敏感品类，资质/标签/宣称任一不合规即触发下架或扣分；有一定复购：刀头/磨头/袋装等配套件可带动二次成交；自有品牌在该品类已有零星在售（2 条，占 7%），说明存在成交但尚未形成压倒性优势，适合抢占头部位置；新手友好：商品好描述、体积小发货轻、决策快，适合铺量上架 | W41: 常规备选，放在长尾分类；用低价冲量，不单独投流
A42: 40 | B42: 你比我猜训练机 | C42: B | D42: 6.19 | E42: 16 | F42: 5 | G42: ¥5–5 | H42: 5 | I42: 1 | J42: 25 | K42: 10 | L42: 30 | M42: 0.37 | N42: 5 | O42: 5.7 | P42: 6.5 | Q42: 6 | R42: 10 | S42: 9 | T42: 6 | U42: =COUNTIF(SKU明细!D3:D607,B42) -> 1 | V42: 需求中等：「想要」人数中位数 10、有想要标签的在售占比 17/30，属于有搜索但竞争平缓的常规位；价格中等：全新竞品中位价 ¥16，主流带 ¥1–25，薄利走量，需控运损；竞争中等：Top30 中出现 0 个不同品牌，需要在主图和标题上做出差异；售后可控：常规小家电，做好成色描述与功能实测视频即可；⚠️ 合规强监管：属强资质敏感品类，资质/标签/宣称任一不合规即触发下架或扣分；有一定复购：刀头/磨头/袋装等配套件可带动二次成交；该品类样本中未见自有品牌在售，属空白位——无内卷，但也需教育市场成本；新手友好：商品好描述、体积小发货轻、决策快，适合铺量上架 | W42: 常规备选，放在长尾分类；用低价冲量，不单独投流
A43: 41 | B43: 多功能沐浴刷 | C43: B | D43: 6.18 | E43: 78 | F43: 56 | G43: ¥50–63 | H43: 48 | I43: 65 | J43: 120 | K43: 10 | L43: 30 | M43: 0.53 | N43: 4.2 | O43: 8.7 | P43: 6.8 | Q43: 2 | R43: 10 | S43: 8 | T43: 5 | U43: =COUNTIF(SKU明细!D3:D607,B43) -> 1 | V43: 需求中等：「想要」人数中位数 10、有想要标签的在售占比 9/30，属于有搜索但竞争平缓的常规位；单件利润空间可观：全新竞品中位价 ¥78，P25–P75 主流带 ¥65–120，有腾挪定价空间；竞争中等：Top30 中出现 1 个不同品牌，需要在主图和标题上做出差异；售后风险极低：非电器或耗材形态，基本无充电/质保/退货纠纷；⚠️ 合规强监管：属强资质敏感品类，资质/标签/宣称任一不合规即触发下架或扣分；有一定复购：刀头/磨头/袋装等配套件可带动二次成交；该品类样本中未见自有品牌在售，属空白位——无内卷，但也需教育市场成本；新手友好：商品好描述、体积小发货轻、决策快，适合铺量上架 | W43: 常规备选，放在长尾分类；用低价冲量，不单独投流
A44: 42 | B44: 封口机袋子 | C44: B | D44: 6.18 | E44: 9 | F44: 6 | G44: ¥4–8 | H44: 4 | I44: 8 | J44: 10 | K44: 4 | L44: 30 | M44: 0.63 | N44: 3.6 | O44: 4.6 | P44: 6.5 | Q44: 8 | R44: 10 | S44: 10 | T44: 10 | U44: =COUNTIF(SKU明细!D3:D607,B44) -> 0 | V44: 需求中等：「想要」人数中位数 4、有想要标签的在售占比 17/30，属于有搜索但竞争平缓的常规位；客单偏低：全新竞品中位价 ¥9，单件利润薄，必须靠走量或组合装摊薄运费；竞争中等：Top30 中出现 1 个不同品牌，需要在主图和标题上做出差异；售后偏高：属电器/易损品类，需提前说明退换规则，建议保留开箱视频；⚠️ 合规强监管：属强资质敏感品类，资质/标签/宣称任一不合规即触发下架或扣分；耗材属性强：可与主机绑定做「主品+耗材」复购套餐，锁定回头客；该品类样本中未见自有品牌在售，属空白位——无内卷，但也需教育市场成本；新手友好：商品好描述、体积小发货轻、决策快，适合铺量上架 | W44: 常规备选，放在长尾分类；用低价冲量，不单独投流
A45: 43 | B45: 筋膜环 | C45: B | D45: 6.16 | E45: 49 | F45: 24 | G45: ¥20–28 | H45: 19 | I45: 28 | J45: 79 | K45: 4 | L45: 30 | M45: 0.77 | N45: 2.8 | O45: 7.8 | P45: 6.8 | Q45: 4 | R45: 7 | S45: 9 | T45: 4 | U45: =COUNTIF(SKU明细!D3:D607,B45) -> 12 | V45: 需求中等：「想要」人数中位数 4、有想要标签的在售占比 9/30，属于有搜索但竞争平缓的常规位；单件利润空间可观：全新竞品中位价 ¥49，P25–P75 主流带 ¥28–79，有腾挪定价空间；竞争中等：Top30 中出现 4 个不同品牌，需要在主图和标题上做出差异；售后风险极低：非电器或耗材形态，基本无充电/质保/退货纠纷；⚠️ 合规强监管：属强资质敏感品类，资质/标签/宣称任一不合规即触发下架或扣分；🔥 自有品牌已在此品类跑通：Top30 竞品中有 7 条是康佳/奥克斯/夏新等自有品牌（占 23%），买家已有认知与搜索基础，上架即有流量基础，试错成本最低；新手友好：商品好描述、体积小发货轻、决策快，适合铺量上架 | W45: 常规备选，放在长尾分类；用低价冲量，不单独投流
A46: 44 | B46: 便携迷你剃须刀 | C46: B | D46: 6.14 | E46: 39 | F46: 28 | G46: ¥24–31 | H46: 23 | I46: 30 | J46: 56 | K46: 3 | L46: 30 | M46: 0.6 | N46: 3.2 | O46: 7.3 | P46: 6.6 | Q46: 2 | R46: 10 | S46: 9 | T46: 4 | U46: =COUNTIF(SKU明细!D3:D607,B46) -> 91 | V46: 需求中等：「想要」人数中位数 3、有想要标签的在售占比 16/30，属于有搜索但竞争平缓的常规位；单件利润空间可观：全新竞品中位价 ¥39，P25–P75 主流带 ¥30–56，有腾挪定价空间；竞争中等：Top30 中出现 5 个不同品牌，需要在主图和标题上做出差异；售后风险极低：非电器或耗材形态，基本无充电/质保/退货纠纷；⚠️ 合规强监管：属强资质敏感品类，资质/标签/宣称任一不合规即触发下架或扣分；🔥 自有品牌已在此品类跑通：Top30 竞品中有 6 条是康佳/奥克斯/夏新等自有品牌（占 20%），买家已有认知与搜索基础，上架即有流量基础，试错成本最低；新手友好：商品好描述、体积小发货轻、决策快，适合铺量上架 | W46: 常规备选，放在长尾分类；用低价冲量，不单独投流
A47: 45 | B47: 电动牙刷 | C47: B | D47: 6.13 | E47: 56 | F47: 28 | G47: ¥14–41 | H47: 13 | I47: 39 | J47: 60 | K47: 3 | L47: 30 | M47: 0.83 | N47: 2.4 | O47: 7.9 | P47: 6.7 | Q47: 3 | R47: 10 | S47: 8 | T47: 7 | U47: =COUNTIF(SKU明细!D3:D607,B47) -> 15 | V47: 需求中等：「想要」人数中位数 3、有想要标签的在售占比 13/30，属于有搜索但竞争平缓的常规位；单件利润空间可观：全新竞品中位价 ¥56，P25–P75 主流带 ¥39–60，有腾挪定价空间；竞争中等：Top30 中出现 5 个不同品牌，需要在主图和标题上做出差异；售后风险极低：非电器或耗材形态，基本无充电/质保/退货纠纷；⚠️ 合规强监管：属强资质敏感品类，资质/标签/宣称任一不合规即触发下架或扣分；有一定复购：刀头/磨头/袋装等配套件可带动二次成交；该品类样本中未见自有品牌在售，属空白位——无内卷，但也需教育市场成本；新手友好：商品好描述、体积小发货轻、决策快，适合铺量上架 | W47: 常规备选，放在长尾分类；用低价冲量，不单独投流
A48: 46 | B48: 手足皲裂膏 | C48: B | D48: 6.1 | E48: 98 | F48: 12 | G48: ¥9–16 | H48: 9 | I48: 16 | J48: 200 | K48: 11.5 | L48: 30 | M48: 0 | N48: 5.2 | O48: 9.1 | P48: 6.4 | Q48: 5 | R48: 1 | S48: 9 | T48: 8 | U48: =COUNTIF(SKU明细!D3:D607,B48) -> 1 | V48: 需求中等：「想要」人数中位数 12、有想要标签的在售占比 20/30，属于有搜索但竞争平缓的常规位；单件利润空间可观：全量竞品中位价 ¥98，P25–P75 主流带 ¥16–200，有腾挪定价空间；竞争中等：Top30 中出现 0 个不同品牌，需要在主图和标题上做出差异；售后可控：常规小家电，做好成色描述与功能实测视频即可；无资质门槛：上架无特殊资质要求，标题可自由发挥；耗材属性强：可与主机绑定做「主品+耗材」复购套餐，锁定回头客；该品类样本中未见自有品牌在售，属空白位——无内卷，但也需教育市场成本；新手友好：商品好描述、体积小发货轻、决策快，适合铺量上架 | W48: 常规备选，放在长尾分类；用低价冲量，不单独投流
A49: 47 | B49: 儿童U型牙刷 | C49: B | D49: 6.09 | E49: 10 | F49: 8 | G49: ¥8–9 | H49: 8 | I49: 9 | J49: 15 | K49: 19.5 | L49: 30 | M49: 0.57 | N49: 6.1 | O49: 4.8 | P49: 6.1 | Q49: 4 | R49: 10 | S49: 8 | T49: 6 | U49: =COUNTIF(SKU明细!D3:D607,B49) -> 3 | V49: 需求中等：「想要」人数中位数 20、有想要标签的在售占比 28/30，属于有搜索但竞争平缓的常规位；客单偏低：全新竞品中位价 ¥10，单件利润薄，必须靠走量或组合装摊薄运费；竞争中等：Top30 中出现 0 个不同品牌，需要在主图和标题上做出差异；售后风险极低：非电器或耗材形态，基本无充电/质保/退货纠纷；⚠️ 合规强监管：属强资质敏感品类，资质/标签/宣称任一不合规即触发下架或扣分；有一定复购：刀头/磨头/袋装等配套件可带动二次成交；该品类样本中未见自有品牌在售，属空白位——无内卷，但也需教育市场成本；新手友好：商品好描述、体积小发货轻、决策快，适合铺量上架 | W49: 常规备选，放在长尾分类；用低价冲量，不单独投流
A50: 48 | B50: 头部按摩器 | C50: B | D50: 6.03 | E50: 35 | F50: 21 | G50: ¥18–24 | H50: 17 | I50: 25 | J50: 60 | K50: 3 | L50: 30 | M50: 0.5 | N50: 2.4 | O50: 7.2 | P50: 6.7 | Q50: 4 | R50: 8 | S50: 8 | T50: 4 | U50: =COUNTIF(SKU明细!D3:D607,B50) -> 1 | V50: 需求中等：「想要」人数中位数 3、有想要标签的在售占比 13/30，属于有搜索但竞争平缓的常规位；单件利润空间可观：全新竞品中位价 ¥35，P25–P75 主流带 ¥25–60，有腾挪定价空间；竞争中等：Top30 中出现 6 个不同品牌，需要在主图和标题上做出差异；售后风险极低：非电器或耗材形态，基本无充电/质保/退货纠纷；⚠️ 合规强监管：属强资质敏感品类，资质/标签/宣称任一不合规即触发下架或扣分；🔥 自有品牌已在此品类跑通：Top30 竞品中有 7 条是康佳/奥克斯/夏新等自有品牌（占 23%），买家已有认知与搜索基础，上架即有流量基础，试错成本最低；新手友好：商品好描述、体积小发货轻、决策快，适合铺量上架 | W50: 常规备选，放在长尾分类；用低价冲量，不单独投流
A51: 49 | B51: 挂烫机 | C51: B | D51: 6.02 | E51: 50 | F51: 21 | G51: ¥20–22 | H51: 19 | I51: 26 | J51: 50 | K51: 6 | L51: 30 | M51: 0.27 | N51: 3.4 | O51: 7.3 | P51: 6.7 | Q51: 2 | R51: 9 | S51: 7 | T51: 6 | U51: =COUNTIF(SKU明细!D3:D607,B51) -> 0 | V51: 需求中等：「想要」人数中位数 6、有想要标签的在售占比 13/30，属于有搜索但竞争平缓的常规位；单件利润空间可观：全新竞品中位价 ¥50，P25–P75 主流带 ¥26–50，有腾挪定价空间；竞争中等：Top30 中出现 5 个不同品牌，需要在主图和标题上做出差异；售后风险极低：非电器或耗材形态，基本无充电/质保/退货纠纷；⚠️ 合规强监管：属强资质敏感品类，资质/标签/宣称任一不合规即触发下架或扣分；有一定复购：刀头/磨头/袋装等配套件可带动二次成交 | W51: 常规备选，放在长尾分类；用低价冲量，不单独投流
A52: 50 | B52: 洁面仪 | C52: B | D52: 5.93 | E52: 29 | F52: 12 | G52: ¥6–18 | H52: 6 | I52: 10 | J52: 39 | K52: 5 | L52: 30 | M52: 0.47 | N52: 3.9 | O52: 6.8 | P52: 6.6 | Q52: 4 | R52: 5 | S52: 9 | T52: 5 | U52: =COUNTIF(SKU明细!D3:D607,B52) -> 2 | V52: 需求中等：「想要」人数中位数 5、有想要标签的在售占比 15/30，属于有搜索但竞争平缓的常规位；价格中等：全新竞品中位价 ¥29，主流带 ¥10–39，薄利走量，需控运损；竞争中等：Top30 中出现 2 个不同品牌，需要在主图和标题上做出差异；售后风险极低：非电器或耗材形态，基本无充电/质保/退货纠纷；宣称需克制：文案避免「治疗/根治/祛斑」等医疗功效词，用「清洁/护理/辅助」表述；有一定复购：刀头/磨头/袋装等配套件可带动二次成交；自有品牌在该品类已有零星在售（2 条，占 7%），说明存在成交但尚未形成压倒性优势，适合抢占头部位置；新手友好：商品好描述、体积小发货轻、决策快，适合铺量上架 | W52: 常规备选，放在长尾分类；用低价冲量，不单独投流
A53: 51 | B53: 电动睫毛卷 | C53: B | D53: 5.92 | E53: 10 | F53: 6 | G53: ¥5–7 | H53: 5 | I53: 7 | J53: 50 | K53: 47.5 | L53: 30 | M53: 0.83 | N53: 6.8 | O53: 4.8 | P53: 6.6 | Q53: 3 | R53: 7 | S53: 9 | T53: 4 | U53: =COUNTIF(SKU明细!D3:D607,B53) -> 14 | V53: 需求中等：「想要」人数中位数 48、有想要标签的在售占比 14/30，属于有搜索但竞争平缓的常规位；客单偏低：全新竞品中位价 ¥10，单件利润薄，必须靠走量或组合装摊薄运费；竞争中等：Top30 中出现 1 个不同品牌，需要在主图和标题上做出差异；售后风险极低：非电器或耗材形态，基本无充电/质保/退货纠纷；⚠️ 合规强监管：属强资质敏感品类，资质/标签/宣称任一不合规即触发下架或扣分；该品类样本中未见自有品牌在售，属空白位——无内卷，但也需教育市场成本；新手友好：商品好描述、体积小发货轻、决策快，适合铺量上架 | W53: 常规备选，放在长尾分类；用低价冲量，不单独投流
A54: 52 | B54: 卷发棒 | C54: B | D54: 5.88 | E54: 30 | F54: 26 | G54: ¥25–28 | H54: 24 | I54: 25 | J54: 36 | K54: 8 | L54: 30 | M54: 0.47 | N54: 3.9 | O54: 6.9 | P54: 6.7 | Q54: 2 | R54: 9 | S54: 8 | T54: 6 | U54: =COUNTIF(SKU明细!D3:D607,B54) -> 0 | V54: 需求中等：「想要」人数中位数 8、有想要标签的在售占比 13/30，属于有搜索但竞争平缓的常规位；价格中等：全新竞品中位价 ¥30，主流带 ¥25–36，薄利走量，需控运损；竞争中等：Top30 中出现 1 个不同品牌，需要在主图和标题上做出差异；售后风险极低：非电器或耗材形态，基本无充电/质保/退货纠纷；⚠️ 合规强监管：属强资质敏感品类，资质/标签/宣称任一不合规即触发下架或扣分；有一定复购：刀头/磨头/袋装等配套件可带动二次成交；该品类样本中未见自有品牌在售，属空白位——无内卷，但也需教育市场成本；新手友好：商品好描述、体积小发货轻、决策快，适合铺量上架 | W54: 常规备选，放在长尾分类；用低价冲量，不单独投流
A55: 53 | B55: 暖菜板 | C55: B | D55: 5.85 | E55: 59 | F55: 44 | G55: ¥41–46 | H55: 39 | I55: 45 | J55: 69 | K55: 6 | L55: 30 | M55: 0.5 | N55: 3.4 | O55: 8.1 | P55: 6.7 | Q55: 3 | R55: 10 | S55: 8 | T55: 5 | U55: =COUNTIF(SKU明细!D3:D607,B55) -> 1 | V55: 需求中等：「想要」人数中位数 6、有想要标签的在售占比 12/30，属于有搜索但竞争平缓的常规位；单件利润空间可观：全新竞品中位价 ¥59，P25–P75 主流带 ¥45–69，有腾挪定价空间；竞争中等：Top30 中出现 3 个不同品牌，需要在主图和标题上做出差异；售后风险极低：非电器或耗材形态，基本无充电/质保/退货纠纷；⚠️ 合规强监管：属强资质敏感品类，资质/标签/宣称任一不合规即触发下架或扣分；有一定复购：刀头/磨头/袋装等配套件可带动二次成交；该品类样本中未见自有品牌在售，属空白位——无内卷，但也需教育市场成本；新手友好：商品好描述、体积小发货轻、决策快，适合铺量上架 | W55: 常规备选，放在长尾分类；用低价冲量，不单独投流
A56: 54 | B56: 牙齿护理仪 | C56: B | D56: 5.83 | E56: 35 | F56: 14 | G56: ¥9–19 | H56: 9 | I56: 18 | J56: 45 | K56: 4 | L56: 30 | M56: 0.53 | N56: 3.6 | O56: 7.2 | P56: 6.5 | Q56: 4 | R56: 3 | S56: 7 | T56: 6 | U56: =COUNTIF(SKU明细!D3:D607,B56) -> 5 | V56: 需求中等：「想要」人数中位数 4、有想要标签的在售占比 17/30，属于有搜索但竞争平缓的常规位；单件利润空间可观：全新竞品中位价 ¥35，P25–P75 主流带 ¥18–45，有腾挪定价空间；竞争中等：Top30 中出现 3 个不同品牌，需要在主图和标题上做出差异；售后风险极低：非电器或耗材形态，基本无充电/质保/退货纠纷；无资质门槛：上架无特殊资质要求，标题可自由发挥；有一定复购：刀头/磨头/袋装等配套件可带动二次成交；自有品牌在该品类已有零星在售（4 条，占 13%），说明存在成交但尚未形成压倒性优势，适合抢占头部位置 | W56: 常规备选，放在长尾分类；用低价冲量，不单独投流
A57: 55 | B57: 筋膜枪 | C57: B | D57: 5.83 | E57: 27 | F57: 18 | G57: ¥16–19 | H57: 15 | I57: 19 | J57: 30 | K57: 4 | L57: 30 | M57: 0.77 | N57: 2.8 | O57: 6.7 | P57: 6.8 | Q57: 3 | R57: 6 | S57: 8 | T57: 4 | U57: =COUNTIF(SKU明细!D3:D607,B57) -> 5 | V57: 需求中等：「想要」人数中位数 4、有想要标签的在售占比 11/30，属于有搜索但竞争平缓的常规位；价格中等：全新竞品中位价 ¥27，主流带 ¥19–30，薄利走量，需控运损；竞争中等：Top30 中出现 4 个不同品牌，需要在主图和标题上做出差异；售后风险极低：非电器或耗材形态，基本无充电/质保/退货纠纷；宣称需克制：文案避免「治疗/根治/祛斑」等医疗功效词，用「清洁/护理/辅助」表述；🔥 自有品牌已在此品类跑通：Top30 竞品中有 13 条是康佳/奥克斯/夏新等自有品牌（占 43%），买家已有认知与搜索基础，上架即有流量基础，试错成本最低；新手友好：商品好描述、体积小发货轻、决策快，适合铺量上架 | W57: 常规备选，放在长尾分类；用低价冲量，不单独投流
A58: 56 | B58: 隐形眼镜清洁盒 | C58: B | D58: 5.83 | E58: 19 | F58: 14 | G58: ¥12–15 | H58: 11 | I58: 15 | J58: 30 | K58: 4.5 | L58: 30 | M58: 0.67 | N58: 3 | O58: 6 | P58: 6.8 | Q58: 7 | R58: 7 | S58: 9 | T58: 8 | U58: =COUNTIF(SKU明细!D3:D607,B58) -> 1 | V58: 需求中等：「想要」人数中位数 4、有想要标签的在售占比 10/30，属于有搜索但竞争平缓的常规位；价格中等：全新竞品中位价 ¥19，主流带 ¥15–30，薄利走量，需控运损；竞争中等：Top30 中出现 0 个不同品牌，需要在主图和标题上做出差异；售后可控：常规小家电，做好成色描述与功能实测视频即可；⚠️ 合规强监管：属强资质敏感品类，资质/标签/宣称任一不合规即触发下架或扣分；耗材属性强：可与主机绑定做「主品+耗材」复购套餐，锁定回头客；该品类样本中未见自有品牌在售，属空白位——无内卷，但也需教育市场成本；新手友好：商品好描述、体积小发货轻、决策快，适合铺量上架 | W58: 常规备选，放在长尾分类；用低价冲量，不单独投流
A59: 57 | B59: 豆浆机 | C59: B | D59: 5.82 | E59: 58 | F59: 34 | G59: ¥21–47 | H59: 20 | I59: 40 | J59: 60 | K59: 9 | L59: 30 | M59: 0.6 | N59: 4 | O59: 8 | P59: 6.9 | Q59: 1 | R59: 9 | S59: 5 | T59: 4 | U59: =COUNTIF(SKU明细!D3:D607,B59) -> 1 | V59: 需求中等：「想要」人数中位数 9、有想要标签的在售占比 8/30，属于有搜索但竞争平缓的常规位；单件利润空间可观：全新竞品中位价 ¥58，P25–P75 主流带 ¥40–60，有腾挪定价空间；竞争中等：Top30 中出现 6 个不同品牌，需要在主图和标题上做出差异；售后风险极低：非电器或耗材形态，基本无充电/质保/退货纠纷；⚠️ 合规强监管：属强资质敏感品类，资质/标签/宣称任一不合规即触发下架或扣分；自有品牌在该品类已有零星在售（2 条，占 7%），说明存在成交但尚未形成压倒性优势，适合抢占头部位置；新手门槛偏高：需讲清参数/尺寸/安装或操作说明，图文投入要足 | W59: 常规备选，放在长尾分类；用低价冲量，不单独投流
A60: 58 | B60: 手持吸尘器 | C60: B | D60: 5.81 | E60: 28 | F60: 12 | G60: ¥10–15 | H60: 10 | I60: 15 | J60: 32 | K60: 9 | L60: 30 | M60: 0.93 | N60: 4 | O60: 6.7 | P60: 6.7 | Q60: 2 | R60: 9 | S60: 7 | T60: 6 | U60: =COUNTIF(SKU明细!D3:D607,B60) -> 6 | V60: 需求中等：「想要」人数中位数 9、有想要标签的在售占比 13/30，属于有搜索但竞争平缓的常规位；价格中等：全新竞品中位价 ¥28，主流带 ¥15–32，薄利走量，需控运损；竞争中等：Top30 中出现 2 个不同品牌，需要在主图和标题上做出差异；售后风险极低：非电器或耗材形态，基本无充电/质保/退货纠纷；⚠️ 合规强监管：属强资质敏感品类，资质/标签/宣称任一不合规即触发下架或扣分；有一定复购：刀头/磨头/袋装等配套件可带动二次成交；该品类样本中未见自有品牌在售，属空白位——无内卷，但也需教育市场成本 | W60: 常规备选，放在长尾分类；用低价冲量，不单独投流
A61: 59 | B61: 超声波洁牙器 | C61: B | D61: 5.8 | E61: 36 | F61: 28 | G61: ¥25–30 | H61: 24 | I61: 25 | J61: 40 | K61: 6 | L61: 30 | M61: 0.43 | N61: 3.4 | O61: 7.2 | P61: 6.6 | Q61: 4 | R61: 3 | S61: 7 | T61: 6 | U61: =COUNTIF(SKU明细!D3:D607,B61) -> 11 | V61: 需求中等：「想要」人数中位数 6、有想要标签的在售占比 14/30，属于有搜索但竞争平缓的常规位；单件利润空间可观：全新竞品中位价 ¥36，P25–P75 主流带 ¥25–40，有腾挪定价空间；竞争中等：Top30 中出现 1 个不同品牌，需要在主图和标题上做出差异；售后风险极低：非电器或耗材形态，基本无充电/质保/退货纠纷；无资质门槛：上架无特殊资质要求，标题可自由发挥；有一定复购：刀头/磨头/袋装等配套件可带动二次成交；自有品牌在该品类已有零星在售（4 条，占 13%），说明存在成交但尚未形成压倒性优势，适合抢占头部位置 | W61: 常规备选，放在长尾分类；用低价冲量，不单独投流
A62: 60 | B62: 化妆刷清洗器 | C62: B | D62: 5.79 | E62: 15 | F62: 4 | G62: ¥3–4 | H62: 3 | I62: 4 | J62: 12 | K62: 11 | L62: 30 | M62: 0.33 | N62: 5.2 | O62: 5.5 | P62: 6.6 | Q62: 5 | R62: 6 | S62: 9 | T62: 6 | U62: =COUNTIF(SKU明细!D3:D607,B62) -> 2 | V62: 需求中等：「想要」人数中位数 11、有想要标签的在售占比 15/30，属于有搜索但竞争平缓的常规位；价格中等：全新竞品中位价 ¥15，主流带 ¥4–12，薄利走量，需控运损；竞争中等：Top30 中出现 0 个不同品牌，需要在主图和标题上做出差异；售后可控：常规小家电，做好成色描述与功能实测视频即可；宣称需克制：文案避免「治疗/根治/祛斑」等医疗功效词，用「清洁/护理/辅助」表述；有一定复购：刀头/磨头/袋装等配套件可带动二次成交；该品类样本中未见自有品牌在售，属空白位——无内卷，但也需教育市场成本；新手友好：商品好描述、体积小发货轻、决策快，适合铺量上架 | W62: 常规备选，放在长尾分类；用低价冲量，不单独投流
A63: 61 | B63: 电动剃须刀 | C63: B | D63: 5.78 | E63: 39 | F63: 26 | G63: ¥24–28 | H63: 23 | I63: 29 | J63: 56 | K63: 4 | L63: 60 | M63: 0.68 | N63: 3.6 | O63: 7.3 | P63: 1.8 | Q63: 2 | R63: 10 | S63: 9 | T63: 5 | U63: =COUNTIF(SKU明细!D3:D607,B63) -> 31 | V63: 需求中等：「想要」人数中位数 4、有想要标签的在售占比 29/30，属于有搜索但竞争平缓的常规位；单件利润空间可观：全新竞品中位价 ¥39，P25–P75 主流带 ¥29–56，有腾挪定价空间；竞争激烈：Top30 里已挤进 10 个品牌，头部品牌已形成价格锚定，正面硬拼不划算；售后风险极低：非电器或耗材形态，基本无充电/质保/退货纠纷；⚠️ 合规强监管：属强资质敏感品类，资质/标签/宣称任一不合规即触发下架或扣分；有一定复购：刀头/磨头/袋装等配套件可带动二次成交；🔥 自有品牌已在此品类跑通：Top30 竞品中有 11 条是康佳/奥克斯/夏新等自有品牌（占 18%），买家已有认知与搜索基础，上架即有流量基础，试错成本最低；新手友好：商品好描述、体积小发货轻、决策快，适合铺量上架 | W63: 常规备选，放在长尾分类；用低价冲量，不单独投流
A64: 62 | B64: 迷你洗衣机 | C64: B | D64: 5.78 | E64: 68 | F64: 24 | G64: ¥18–31 | H64: 17 | I64: 35 | J64: 84 | K64: 7 | L64: 30 | M64: 0.77 | N64: 4.4 | O64: 8.2 | P64: 6.5 | Q64: 1 | R64: 9 | S64: 5 | T64: 4 | U64: =COUNTIF(SKU明细!D3:D607,B64) -> 2 | V64: 需求中等：「想要」人数中位数 7、有想要标签的在售占比 17/30，属于有搜索但竞争平缓的常规位；单件利润空间可观：全新竞品中位价 ¥68，P25–P75 主流带 ¥35–84，有腾挪定价空间；竞争中等：Top30 中出现 3 个不同品牌，需要在主图和标题上做出差异；售后风险极低：非电器或耗材形态，基本无充电/质保/退货纠纷；⚠️ 合规强监管：属强资质敏感品类，资质/标签/宣称任一不合规即触发下架或扣分；新手门槛偏高：需讲清参数/尺寸/安装或操作说明，图文投入要足 | W64: 常规备选，放在长尾分类；用低价冲量，不单独投流
A65: 63 | B65: 刮痧仪 | C65: B | D65: 5.77 | E65: 26 | F65: 18 | G65: ¥15–20 | H65: 14 | I65: 18 | J65: 30 | K65: 3 | L65: 30 | M65: 0.67 | N65: 3.2 | O65: 6.6 | P65: 6.6 | Q65: 3 | R65: 6 | S65: 8 | T65: 4 | U65: =COUNTIF(SKU明细!D3:D607,B65) -> 0 | V65: 需求中等：「想要」人数中位数 3、有想要标签的在售占比 15/30，属于有搜索但竞争平缓的常规位；价格中等：全新竞品中位价 ¥26，主流带 ¥18–30，薄利走量，需控运损；竞争中等：Top30 中出现 2 个不同品牌，需要在主图和标题上做出差异；售后风险极低：非电器或耗材形态，基本无充电/质保/退货纠纷；宣称需克制：文案避免「治疗/根治/祛斑」等医疗功效词，用「清洁/护理/辅助」表述；🔥 自有品牌已在此品类跑通：Top30 竞品中有 7 条是康佳/奥克斯/夏新等自有品牌（占 23%），买家已有认知与搜索基础，上架即有流量基础，试错成本最低；新手友好：商品好描述、体积小发货轻、决策快，适合铺量上架 | W65: 常规备选，放在长尾分类；用低价冲量，不单独投流
A66: 64 | B66: 冰点脱毛仪 | C66: B | D66: 5.76 | E66: 29 | F66: 12 | G66: ¥3–22 | H66: 3 | I66: 15 | J66: 195 | K66: 26 | L66: 30 | M66: 0.3 | N66: 6.6 | O66: 6.8 | P66: 6.6 | Q66: 4 | R66: 1 | S66: 6 | T66: 4 | U66: =COUNTIF(SKU明细!D3:D607,B66) -> 2 | V66: 需求中等：「想要」人数中位数 26、有想要标签的在售占比 16/30，属于有搜索但竞争平缓的常规位；价格中等：全新竞品中位价 ¥29，主流带 ¥15–195，薄利走量，需控运损；竞争中等：Top30 中出现 1 个不同品牌，需要在主图和标题上做出差异；售后风险极低：非电器或耗材形态，基本无充电/质保/退货纠纷；无资质门槛：上架无特殊资质要求，标题可自由发挥；该品类样本中未见自有品牌在售，属空白位——无内卷，但也需教育市场成本 | W66: 常规备选，放在长尾分类；用低价冲量，不单独投流
A67: 65 | B67: 电动拖把 | C67: B | D67: 5.76 | E67: 76 | F67: 60 | G67: ¥50–70 | H67: 48 | I67: 68 | J67: 99 | K67: 4 | L67: 30 | M67: 0.3 | N67: 2.8 | O67: 8.7 | P67: 6.8 | Q67: 2 | R67: 9 | S67: 6 | T67: 5 | U67: =COUNTIF(SKU明细!D3:D607,B67) -> 0 | V67: 需求中等：「想要」人数中位数 4、有想要标签的在售占比 11/30，属于有搜索但竞争平缓的常规位；单件利润空间可观：全新竞品中位价 ¥76，P25–P75 主流带 ¥68–99，有腾挪定价空间；竞争中等：Top30 中出现 3 个不同品牌，需要在主图和标题上做出差异；售后风险极低：非电器或耗材形态，基本无充电/质保/退货纠纷；⚠️ 合规强监管：属强资质敏感品类，资质/标签/宣称任一不合规即触发下架或扣分；有一定复购：刀头/磨头/袋装等配套件可带动二次成交；该品类样本中未见自有品牌在售，属空白位——无内卷，但也需教育市场成本 | W67: 常规备选，放在长尾分类；用低价冲量，不单独投流
A68: 66 | B68: 按摩枕 | C68: B | D68: 5.74 | E68: 50 | F68: 22 | G68: ¥17–26 | H68: 16 | I68: 28 | J68: 60 | K68: 2 | L68: 30 | M68: 0.7 | N68: 1.9 | O68: 7.6 | P68: 6.9 | Q68: 3 | R68: 8 | S68: 7 | T68: 3 | U68: =COUNTIF(SKU明细!D3:D607,B68) -> 2 | V68: 需求中等：「想要」人数中位数 2、有想要标签的在售占比 7/30，属于有搜索但竞争平缓的常规位；单件利润空间可观：全新竞品中位价 ¥50，P25–P75 主流带 ¥28–60，有腾挪定价空间；竞争中等：Top30 中出现 2 个不同品牌，需要在主图和标题上做出差异；售后风险极低：非电器或耗材形态，基本无充电/质保/退货纠纷；⚠️ 合规强监管：属强资质敏感品类，资质/标签/宣称任一不合规即触发下架或扣分；🔥 自有品牌已在此品类跑通：Top30 竞品中有 13 条是康佳/奥克斯/夏新等自有品牌（占 43%），买家已有认知与搜索基础，上架即有流量基础，试错成本最低 | W68: 常规备选，放在长尾分类；用低价冲量，不单独投流
A69: 67 | B69: 每日悬灸 | C69: B | D69: 5.63 | E69: 19 | F69: 12 | G69: ¥9–15 | H69: 9 | I69: 12 | J69: 26 | K69: 16 | L69: 30 | M69: 0.8 | N69: 5 | O69: 6 | P69: 6.8 | Q69: 4 | R69: 3 | S69: 8 | T69: 7 | U69: =COUNTIF(SKU明细!D3:D607,B69) -> 1 | V69: 需求中等：「想要」人数中位数 16、有想要标签的在售占比 11/30，属于有搜索但竞争平缓的常规位；价格中等：全新竞品中位价 ¥19，主流带 ¥12–26，薄利走量，需控运损；竞争中等：Top30 中出现 1 个不同品牌，需要在主图和标题上做出差异；售后风险极低：非电器或耗材形态，基本无充电/质保/退货纠纷；无资质门槛：上架无特殊资质要求，标题可自由发挥；有一定复购：刀头/磨头/袋装等配套件可带动二次成交；新手友好：商品好描述、体积小发货轻、决策快，适合铺量上架 | W69: 常规备选，放在长尾分类；用低价冲量，不单独投流
A70: 68 | B70: 驱蚊手环 | C70: B | D70: 5.6 | E70: 17 | F70: 10 | G70: ¥9–10 | H70: 9 | I70: 9 | J70: 19 | K70: 6 | L70: 30 | M70: 0.5 | N70: 3.4 | O70: 5.8 | P70: 6.8 | Q70: 6 | R70: 7 | S70: 9 | T70: 5 | U70: =COUNTIF(SKU明细!D3:D607,B70) -> 2 | V70: 需求中等：「想要」人数中位数 6、有想要标签的在售占比 11/30，属于有搜索但竞争平缓的常规位；价格中等：全新竞品中位价 ¥17，主流带 ¥9–19，薄利走量，需控运损；竞争中等：Top30 中出现 0 个不同品牌，需要在主图和标题上做出差异；售后可控：常规小家电，做好成色描述与功能实测视频即可；⚠️ 合规强监管：属强资质敏感品类，资质/标签/宣称任一不合规即触发下架或扣分；有一定复购：刀头/磨头/袋装等配套件可带动二次成交；该品类样本中未见自有品牌在售，属空白位——无内卷，但也需教育市场成本；新手友好：商品好描述、体积小发货轻、决策快，适合铺量上架 | W70: 常规备选，放在长尾分类；用低价冲量，不单独投流
A71: 69 | B71: 理发器 | C71: B | D71: 5.59 | E71: 38 | F71: 22 | G71: ¥19–25 | H71: 18 | I71: 25 | J71: 44 | K71: 4 | L71: 60 | M71: 0.67 | N71: 3.6 | O71: 7.3 | P71: 3.6 | Q71: 2 | R71: 10 | S71: 8 | T71: 5 | U71: =COUNTIF(SKU明细!D3:D607,B71) -> 26 | V71: 需求中等：「想要」人数中位数 4、有想要标签的在售占比 21/30，属于有搜索但竞争平缓的常规位；单件利润空间可观：全新竞品中位价 ¥38，P25–P75 主流带 ¥25–44，有腾挪定价空间；竞争激烈：Top30 里已挤进 6 个品牌，头部品牌已形成价格锚定，正面硬拼不划算；售后风险极低：非电器或耗材形态，基本无充电/质保/退货纠纷；⚠️ 合规强监管：属强资质敏感品类，资质/标签/宣称任一不合规即触发下架或扣分；有一定复购：刀头/磨头/袋装等配套件可带动二次成交；自有品牌在该品类已有零星在售（5 条，占 8%），说明存在成交但尚未形成压倒性优势，适合抢占头部位置；新手友好：商品好描述、体积小发货轻、决策快，适合铺量上架 | W71: 常规备选，放在长尾分类；用低价冲量，不单独投流
A72: 70 | B72: 黑头仪 | C72: B | D72: 5.55 | E72: 36 | F72: 22 | G72: ¥17–27 | H72: 16 | I72: 19 | J72: 39 | K72: 2.5 | L72: 30 | M72: 0.57 | N72: 2.2 | O72: 7 | P72: 6.7 | Q72: 4 | R72: 4 | S72: 8 | T72: 4 | U72: =COUNTIF(SKU明细!D3:D607,B72) -> 5 | V72: 需求中等：「想要」人数中位数 2、有想要标签的在售占比 12/30，属于有搜索但竞争平缓的常规位；单件利润空间可观：全新竞品中位价 ¥36，P25–P75 主流带 ¥19–39，有腾挪定价空间；竞争中等：Top30 中出现 3 个不同品牌，需要在主图和标题上做出差异；售后风险极低：非电器或耗材形态，基本无充电/质保/退货纠纷；宣称需克制：文案避免「治疗/根治/祛斑」等医疗功效词，用「清洁/护理/辅助」表述；🔥 自有品牌已在此品类跑通：Top30 竞品中有 16 条是康佳/奥克斯/夏新等自有品牌（占 53%），买家已有认知与搜索基础，上架即有流量基础，试错成本最低；新手友好：商品好描述、体积小发货轻、决策快，适合铺量上架 | W72: 常规备选，放在长尾分类；用低价冲量，不单独投流
A73: 71 | B73: 洗眼液 | C73: B | D73: 5.54 | E73: 18 | F73: 12 | G73: ¥10–13 | H73: 10 | I73: 13 | J73: 25 | K73: 18.5 | L73: 30 | M73: 0.8 | N73: 5.2 | O73: 5.9 | P73: 6.8 | Q73: 5 | R73: 1 | S73: 8 | T73: 8 | U73: =COUNTIF(SKU明细!D3:D607,B73) -> 1 | V73: 需求中等：「想要」人数中位数 18、有想要标签的在售占比 10/30，属于有搜索但竞争平缓的常规位；价格中等：全新竞品中位价 ¥18，主流带 ¥13–25，薄利走量，需控运损；竞争中等：Top30 中出现 0 个不同品牌，需要在主图和标题上做出差异；售后可控：常规小家电，做好成色描述与功能实测视频即可；无资质门槛：上架无特殊资质要求，标题可自由发挥；耗材属性强：可与主机绑定做「主品+耗材」复购套餐，锁定回头客；该品类样本中未见自有品牌在售，属空白位——无内卷，但也需教育市场成本；新手友好：商品好描述、体积小发货轻、决策快，适合铺量上架 | W73: 常规备选，放在长尾分类；用低价冲量，不单独投流
A74: 72 | B74: 多功能电动磨甲器 | C74: B | D74: 5.51 | E74: 23 | F74: 12 | G74: ¥9–15 | H74: 9 | I74: 13 | J74: 28 | K74: 6 | L74: 30 | M74: 0.63 | N74: 3.4 | O74: 6.3 | P74: 6.9 | Q74: 2 | R74: 10 | S74: 8 | T74: 5 | U74: =COUNTIF(SKU明细!D3:D607,B74) -> 0 | V74: 需求中等：「想要」人数中位数 6、有想要标签的在售占比 8/30，属于有搜索但竞争平缓的常规位；价格中等：全新竞品中位价 ¥23，主流带 ¥13–28，薄利走量，需控运损；竞争中等：Top30 中出现 0 个不同品牌，需要在主图和标题上做出差异；售后风险极低：非电器或耗材形态，基本无充电/质保/退货纠纷；⚠️ 合规强监管：属强资质敏感品类，资质/标签/宣称任一不合规即触发下架或扣分；有一定复购：刀头/磨头/袋装等配套件可带动二次成交；该品类样本中未见自有品牌在售，属空白位——无内卷，但也需教育市场成本；新手友好：商品好描述、体积小发货轻、决策快，适合铺量上架 | W74: 常规备选，放在长尾分类；用低价冲量，不单独投流
A75: 73 | B75: 婴儿理发器 | C75: B | D75: 5.51 | E75: 40 | F75: 28 | G75: ¥23–34 | H75: 22 | I75: 35 | J75: 49 | K75: 2 | L75: 30 | M75: 0.63 | N75: 1.9 | O75: 7.4 | P75: 6.8 | Q75: 3 | R75: 10 | S75: 8 | T75: 4 | U75: =COUNTIF(SKU明细!D3:D607,B75) -> 0 | V75: 需求中等：「想要」人数中位数 2、有想要标签的在售占比 11/30，属于有搜索但竞争平缓的常规位；单件利润空间可观：全新竞品中位价 ¥40，P25–P75 主流带 ¥35–49，有腾挪定价空间；竞争中等：Top30 中出现 1 个不同品牌，需要在主图和标题上做出差异；售后风险极低：非电器或耗材形态，基本无充电/质保/退货纠纷；⚠️ 合规强监管：属强资质敏感品类，资质/标签/宣称任一不合规即触发下架或扣分；该品类样本中未见自有品牌在售，属空白位——无内卷，但也需教育市场成本；新手友好：商品好描述、体积小发货轻、决策快，适合铺量上架 | W75: 常规备选，放在长尾分类；用低价冲量，不单独投流
A76: 74 | B76: 女士剃毛器 | C76: B | D76: 5.5 | E76: 20 | F76: 16 | G76: ¥15–16 | H76: 14 | I76: 15 | J76: 23 | K76: 2 | L76: 30 | M76: 0.7 | N76: 1.9 | O76: 6.1 | P76: 6.8 | Q76: 2 | R76: 10 | S76: 8 | T76: 4 | U76: =COUNTIF(SKU明细!D3:D607,B76) -> 0 | V76: 需求中等：「想要」人数中位数 2、有想要标签的在售占比 10/30，属于有搜索但竞争平缓的常规位；价格中等：全新竞品中位价 ¥20，主流带 ¥15–23，薄利走量，需控运损；竞争中等：Top30 中出现 4 个不同品牌，需要在主图和标题上做出差异；售后风险极低：非电器或耗材形态，基本无充电/质保/退货纠纷；⚠️ 合规强监管：属强资质敏感品类，资质/标签/宣称任一不合规即触发下架或扣分；🔥 自有品牌已在此品类跑通：Top30 竞品中有 9 条是康佳/奥克斯/夏新等自有品牌（占 30%），买家已有认知与搜索基础，上架即有流量基础，试错成本最低；新手友好：商品好描述、体积小发货轻、决策快，适合铺量上架 | W76: 常规备选，放在长尾分类；用低价冲量，不单独投流
A77: 75 | B77: 鼻毛修剪器 | C77: B | D77: 5.49 | E77: 15 | F77: 12 | G77: ¥10–15 | H77: 10 | I77: 14 | J77: 20 | K77: 2 | L77: 30 | M77: 0.77 | N77: 1.9 | O77: 5.5 | P77: 6.8 | Q77: 2 | R77: 10 | S77: 9 | T77: 4 | U77: =COUNTIF(SKU明细!D3:D607,B77) -> 43 | V77: 需求中等：「想要」人数中位数 2、有想要标签的在售占比 10/30，属于有搜索但竞争平缓的常规位；价格中等：全新竞品中位价 ¥15，主流带 ¥14–20，薄利走量，需控运损；竞争中等：Top30 中出现 5 个不同品牌，需要在主图和标题上做出差异；售后风险极低：非电器或耗材形态，基本无充电/质保/退货纠纷；⚠️ 合规强监管：属强资质敏感品类，资质/标签/宣称任一不合规即触发下架或扣分；自有品牌在该品类已有零星在售（3 条，占 10%），说明存在成交但尚未形成压倒性优势，适合抢占头部位置；新手友好：商品好描述、体积小发货轻、决策快，适合铺量上架 | W77: 常规备选，放在长尾分类；用低价冲量，不单独投流
A78: 76 | B78: 智能走罐按摩器 | C78: B | D78: 5.48 | E78: 36 | F78: 24 | G78: ¥18–29 | H78: 17 | I78: 29 | J78: 59 | K78: 4 | L78: 30 | M78: 0.7 | N78: 2.8 | O78: 7.2 | P78: 6.8 | Q78: 3 | R78: 6 | S78: 7 | T78: 4 | U78: =COUNTIF(SKU明细!D3:D607,B78) -> 2 | V78: 需求中等：「想要」人数中位数 4、有想要标签的在售占比 10/30，属于有搜索但竞争平缓的常规位；单件利润空间可观：全新竞品中位价 ¥36，P25–P75 主流带 ¥29–59，有腾挪定价空间；竞争中等：Top30 中出现 4 个不同品牌，需要在主图和标题上做出差异；售后风险极低：非电器或耗材形态，基本无充电/质保/退货纠纷；宣称需克制：文案避免「治疗/根治/祛斑」等医疗功效词，用「清洁/护理/辅助」表述；自有品牌在该品类已有零星在售（2 条，占 7%），说明存在成交但尚未形成压倒性优势，适合抢占头部位置 | W78: 常规备选，放在长尾分类；用低价冲量，不单独投流
A79: 77 | B79: 筋膜按摩贴 | C79: B | D79: 5.48 | E79: 25 | F79: 16 | G79: ¥14–17 | H79: 13 | I79: 18 | J79: 50 | K79: 12 | L79: 30 | M79: 0.73 | N79: 4.5 | O79: 6.4 | P79: 6.9 | Q79: 4 | R79: 4 | S79: 9 | T79: 3 | U79: =COUNTIF(SKU明细!D3:D607,B79) -> 7 | V79: 需求中等：「想要」人数中位数 12、有想要标签的在售占比 7/30，属于有搜索但竞争平缓的常规位；价格中等：全新竞品中位价 ¥25，主流带 ¥18–50，薄利走量，需控运损；竞争中等：Top30 中出现 2 个不同品牌，需要在主图和标题上做出差异；售后风险极低：非电器或耗材形态，基本无充电/质保/退货纠纷；宣称需克制：文案避免「治疗/根治/祛斑」等医疗功效词，用「清洁/护理/辅助」表述；该品类样本中未见自有品牌在售，属空白位——无内卷，但也需教育市场成本；新手友好：商品好描述、体积小发货轻、决策快，适合铺量上架 | W79: 常规备选，放在长尾分类；用低价冲量，不单独投流
A80: 78 | B80: 艾柱 | C80: B | D80: 5.47 | E80: 18 | F80: 9 | G80: ¥8–10 | H80: 8 | I80: 9 | J80: 19 | K80: 7 | L80: 30 | M80: 0.5 | N80: 4.4 | O80: 5.9 | P80: 6.6 | Q80: 5 | R80: 3 | S80: 9 | T80: 8 | U80: =COUNTIF(SKU明细!D3:D607,B80) -> 1 | V80: 需求中等：「想要」人数中位数 7、有想要标签的在售占比 16/30，属于有搜索但竞争平缓的常规位；价格中等：全新竞品中位价 ¥18，主流带 ¥9–19，薄利走量，需控运损；竞争中等：Top30 中出现 0 个不同品牌，需要在主图和标题上做出差异；售后可控：常规小家电，做好成色描述与功能实测视频即可；无资质门槛：上架无特殊资质要求，标题可自由发挥；耗材属性强：可与主机绑定做「主品+耗材」复购套餐，锁定回头客；该品类样本中未见自有品牌在售，属空白位——无内卷，但也需教育市场成本；新手友好：商品好描述、体积小发货轻、决策快，适合铺量上架 | W80: 常规备选，放在长尾分类；用低价冲量，不单独投流
A81: 79 | B81: 芦荟胶 | C81: B | D81: 5.43 | E81: 18 | F81: 11 | G81: ¥7–15 | H81: 7 | I81: 15 | J81: 19 | K81: 16 | L81: 30 | M81: 0.8 | N81: 5 | O81: 5.9 | P81: 6.7 | Q81: 5 | R81: 1 | S81: 9 | T81: 8 | U81: =COUNTIF(SKU明细!D3:D607,B81) -> 1 | V81: 需求中等：「想要」人数中位数 16、有想要标签的在售占比 13/30，属于有搜索但竞争平缓的常规位；价格中等：全新竞品中位价 ¥18，主流带 ¥15–19，薄利走量，需控运损；竞争中等：Top30 中出现 0 个不同品牌，需要在主图和标题上做出差异；售后可控：常规小家电，做好成色描述与功能实测视频即可；无资质门槛：上架无特殊资质要求，标题可自由发挥；耗材属性强：可与主机绑定做「主品+耗材」复购套餐，锁定回头客；该品类样本中未见自有品牌在售，属空白位——无内卷，但也需教育市场成本；新手友好：商品好描述、体积小发货轻、决策快，适合铺量上架 | W81: 常规备选，放在长尾分类；用低价冲量，不单独投流
A82: 80 | B82: 小风扇 | C82: B | D82: 5.42 | E82: 9 | F82: 7 | G82: ¥6–8 | H82: 6 | I82: 8 | J82: 13 | K82: 10.5 | L82: 30 | M82: 0.7 | N82: 4.3 | O82: 4.6 | P82: 6.7 | Q82: 3 | R82: 10 | S82: 9 | T82: 4 | U82: =COUNTIF(SKU明细!D3:D607,B82) -> 3 | V82: 需求中等：「想要」人数中位数 10、有想要标签的在售占比 12/30，属于有搜索但竞争平缓的常规位；客单偏低：全新竞品中位价 ¥9，单件利润薄，必须靠走量或组合装摊薄运费；竞争中等：Top30 中出现 1 个不同品牌，需要在主图和标题上做出差异；售后风险极低：非电器或耗材形态，基本无充电/质保/退货纠纷；⚠️ 合规强监管：属强资质敏感品类，资质/标签/宣称任一不合规即触发下架或扣分；该品类样本中未见自有品牌在售，属空白位——无内卷，但也需教育市场成本；新手友好：商品好描述、体积小发货轻、决策快，适合铺量上架 | W82: 常规备选，放在长尾分类；用低价冲量，不单独投流
A83: 81 | B83: 除螨仪 | C83: B | D83: 5.42 | E83: 75 | F83: 52 | G83: ¥45–58 | H83: 43 | I83: 58 | J83: 99 | K83: 3 | L83: 30 | M83: 0 | N83: 2.4 | O83: 8.6 | P83: 6.8 | Q83: 3 | R83: 6 | S83: 7 | T83: 4 | U83: =COUNTIF(SKU明细!D3:D607,B83) -> 3 | V83: 需求中等：「想要」人数中位数 3、有想要标签的在售占比 10/30，属于有搜索但竞争平缓的常规位；单件利润空间可观：全量竞品中位价 ¥75，P25–P75 主流带 ¥58–99，有腾挪定价空间；竞争中等：Top30 中出现 5 个不同品牌，需要在主图和标题上做出差异；售后风险极低：非电器或耗材形态，基本无充电/质保/退货纠纷；宣称需克制：文案避免「治疗/根治/祛斑」等医疗功效词，用「清洁/护理/辅助」表述；该品类样本中未见自有品牌在售，属空白位——无内卷，但也需教育市场成本 | W83: 常规备选，放在长尾分类；用低价冲量，不单独投流
A84: 82 | B84: 迷你拖把 | C84: B | D84: 5.41 | E84: 16 | F84: 7 | G84: ¥5–9 | H84: 5 | I84: 7 | J84: 19 | K84: 7 | L84: 30 | M84: 0.53 | N84: 3.6 | O84: 5.7 | P84: 6.6 | Q84: 3 | R84: 10 | S84: 8 | T84: 5 | U84: =COUNTIF(SKU明细!D3:D607,B84) -> 1 | V84: 需求中等：「想要」人数中位数 7、有想要标签的在售占比 14/30，属于有搜索但竞争平缓的常规位；价格中等：全新竞品中位价 ¥16，主流带 ¥7–19，薄利走量，需控运损；竞争中等：Top30 中出现 2 个不同品牌，需要在主图和标题上做出差异；售后风险极低：非电器或耗材形态，基本无充电/质保/退货纠纷；⚠️ 合规强监管：属强资质敏感品类，资质/标签/宣称任一不合规即触发下架或扣分；有一定复购：刀头/磨头/袋装等配套件可带动二次成交；该品类样本中未见自有品牌在售，属空白位——无内卷，但也需教育市场成本；新手友好：商品好描述、体积小发货轻、决策快，适合铺量上架 | W84: 常规备选，放在长尾分类；用低价冲量，不单独投流
A85: 83 | B85: 电动清洁刷 | C85: C | D85: 5.35 | E85: 25 | F85: 14 | G85: ¥12–16 | H85: 11 | I85: 15 | J85: 50 | K85: 4 | L85: 30 | M85: 0.83 | N85: 2.8 | O85: 6.5 | P85: 6.7 | Q85: 2 | R85: 10 | S85: 8 | T85: 5 | U85: =COUNTIF(SKU明细!D3:D607,B85) -> 1 | V85: 需求偏冷：「想要」人数中位数仅 4，自然流量薄弱，靠搜索自然成交难度大，需搭配低价或搭售；价格中等：全新竞品中位价 ¥25，主流带 ¥15–50，薄利走量，需控运损；竞争中等：Top30 中出现 0 个不同品牌，需要在主图和标题上做出差异；售后风险极低：非电器或耗材形态，基本无充电/质保/退货纠纷；⚠️ 合规强监管：属强资质敏感品类，资质/标签/宣称任一不合规即触发下架或扣分；有一定复购：刀头/磨头/袋装等配套件可带动二次成交；该品类样本中未见自有品牌在售，属空白位——无内卷，但也需教育市场成本；新手友好：商品好描述、体积小发货轻、决策快，适合铺量上架 | W85: 谨慎试水：少量上架测款，只有当月出单才补货；写清「瑕疵/为什么低价」
A86: 84 | B86: 电动剃毛器 | C86: C | D86: 5.33 | E86: 27 | F86: 18 | G86: ¥15–20 | H86: 14 | I86: 19 | J86: 35 | K86: 2 | L86: 60 | M86: 0.77 | N86: 2.7 | O86: 6.7 | P86: 3.7 | Q86: 2 | R86: 10 | S86: 8 | T86: 4 | U86: =COUNTIF(SKU明细!D3:D607,B86) -> 28 | V86: 需求偏冷：「想要」人数中位数仅 2，自然流量薄弱，靠搜索自然成交难度大，需搭配低价或搭售；价格中等：全新竞品中位价 ¥27，主流带 ¥19–35，薄利走量，需控运损；竞争激烈：Top30 里已挤进 6 个品牌，头部品牌已形成价格锚定，正面硬拼不划算；售后风险极低：非电器或耗材形态，基本无充电/质保/退货纠纷；⚠️ 合规强监管：属强资质敏感品类，资质/标签/宣称任一不合规即触发下架或扣分；🔥 自有品牌已在此品类跑通：Top30 竞品中有 14 条是康佳/奥克斯/夏新等自有品牌（占 23%），买家已有认知与搜索基础，上架即有流量基础，试错成本最低；新手友好：商品好描述、体积小发货轻、决策快，适合铺量上架 | W86: 谨慎试水：少量上架测款，只有当月出单才补货；写清「瑕疵/为什么低价」
A87: 85 | B87: 美颈仪 | C87: C | D87: 5.33 | E87: 254 | F87: 188 | G87: ¥187–189 | H87: 178 | I87: 220 | J87: 299 | K87: 1 | L87: 30 | M87: 0.77 | N87: 1.2 | O87: 10 | P87: 6.9 | Q87: 4 | R87: 4 | S87: 7 | T87: 4 | U87: =COUNTIF(SKU明细!D3:D607,B87) -> 3 | V87: 需求偏冷：「想要」人数中位数仅 1，自然流量薄弱，靠搜索自然成交难度大，需搭配低价或搭售；单件利润空间可观：全新竞品中位价 ¥254，P25–P75 主流带 ¥220–299，有腾挪定价空间；竞争中等：Top30 中出现 0 个不同品牌，需要在主图和标题上做出差异；售后风险极低：非电器或耗材形态，基本无充电/质保/退货纠纷；宣称需克制：文案避免「治疗/根治/祛斑」等医疗功效词，用「清洁/护理/辅助」表述；该品类样本中未见自有品牌在售，属空白位——无内卷，但也需教育市场成本 | W87: 谨慎试水：少量上架测款，只有当月出单才补货；写清「瑕疵/为什么低价」
A88: 86 | B88: 甩脂机 | C88: C | D88: 5.31 | E88: 59 | F88: 46 | G88: ¥41–50 | H88: 39 | I88: 48 | J88: 63 | K88: 4.5 | L88: 30 | M88: 0.4 | N88: 3 | O88: 8.2 | P88: 6.8 | Q88: 3 | R88: 2 | S88: 6 | T88: 3 | U88: =COUNTIF(SKU明细!D3:D607,B88) -> 2 | V88: 需求偏冷：「想要」人数中位数仅 4，自然流量薄弱，靠搜索自然成交难度大，需搭配低价或搭售；单件利润空间可观：全新竞品中位价 ¥59，P25–P75 主流带 ¥48–63，有腾挪定价空间；竞争中等：Top30 中出现 1 个不同品牌，需要在主图和标题上做出差异；售后风险极低：非电器或耗材形态，基本无充电/质保/退货纠纷；无资质门槛：上架无特殊资质要求，标题可自由发挥；自有品牌在该品类已有零星在售（4 条，占 13%），说明存在成交但尚未形成压倒性优势，适合抢占头部位置 | W88: 谨慎试水：少量上架测款，只有当月出单才补货；写清「瑕疵/为什么低价」
A89: 87 | B89: 智能护膝仪 | C89: C | D89: 5.27 | E89: 100 | F89: 38 | G89: ¥36–41 | H89: 34 | I89: 41 | J89: 139 | K89: 4 | L89: 30 | M89: 0.7 | N89: 2.8 | O89: 9.2 | P89: 6.8 | Q89: 3 | R89: 4 | S89: 7 | T89: 3 | U89: =COUNTIF(SKU明细!D3:D607,B89) -> 1 | V89: 需求偏冷：「想要」人数中位数仅 4，自然流量薄弱，靠搜索自然成交难度大，需搭配低价或搭售；单件利润空间可观：全新竞品中位价 ¥100，P25–P75 主流带 ¥41–139，有腾挪定价空间；竞争中等：Top30 中出现 0 个不同品牌，需要在主图和标题上做出差异；售后风险极低：非电器或耗材形态，基本无充电/质保/退货纠纷；宣称需克制：文案避免「治疗/根治/祛斑」等医疗功效词，用「清洁/护理/辅助」表述；该品类样本中未见自有品牌在售，属空白位——无内卷，但也需教育市场成本 | W89: 谨慎试水：少量上架测款，只有当月出单才补货；写清「瑕疵/为什么低价」
A90: 88 | B90: 冰丝口罩 | C90: C | D90: 5.25 | E90: 14 | F90: 7 | G90: ¥7–7 | H90: 7 | I90: 9 | J90: 17 | K90: 5 | L90: 30 | M90: 0.73 | N90: 3.1 | O90: 5 | P90: 6.7 | Q90: 5 | R90: 5 | S90: 9 | T90: 7 | U90: =COUNTIF(SKU明细!D3:D607,B90) -> 3 | V90: 需求偏冷：「想要」人数中位数仅 5，自然流量薄弱，靠搜索自然成交难度大，需搭配低价或搭售；价格中等：全新竞品中位价 ¥14，主流带 ¥9–17，薄利走量，需控运损；竞争中等：Top30 中出现 2 个不同品牌，需要在主图和标题上做出差异；售后可控：常规小家电，做好成色描述与功能实测视频即可；宣称需克制：文案避免「治疗/根治/祛斑」等医疗功效词，用「清洁/护理/辅助」表述；有一定复购：刀头/磨头/袋装等配套件可带动二次成交；该品类样本中未见自有品牌在售，属空白位——无内卷，但也需教育市场成本；新手友好：商品好描述、体积小发货轻、决策快，适合铺量上架 | W90: 谨慎试水：少量上架测款，只有当月出单才补货；写清「瑕疵/为什么低价」
A91: 89 | B91: 强脉冲光治疗仪 | C91: C | D91: 5.24 | E91: 60 | F91: 12 | G91: ¥12–13 | H91: 11 | I91: 16 | J91: 56 | K91: 5 | L91: 30 | M91: 0.33 | N91: 3.1 | O91: 7.8 | P91: 6.9 | Q91: 4 | R91: 1 | S91: 5 | T91: 3 | U91: =COUNTIF(SKU明细!D3:D607,B91) -> 2 | V91: 需求偏冷：「想要」人数中位数仅 5，自然流量薄弱，靠搜索自然成交难度大，需搭配低价或搭售；单件利润空间可观：全新竞品中位价 ¥60，P25–P75 主流带 ¥16–56，有腾挪定价空间；竞争中等：Top30 中出现 1 个不同品牌，需要在主图和标题上做出差异；售后风险极低：非电器或耗材形态，基本无充电/质保/退货纠纷；无资质门槛：上架无特殊资质要求，标题可自由发挥；新手门槛偏高：需讲清参数/尺寸/安装或操作说明，图文投入要足 | W91: 谨慎试水：少量上架测款，只有当月出单才补货；写清「瑕疵/为什么低价」
A92: 90 | B92: 漱口水 | C92: C | D92: 5.23 | E92: 16 | F92: 10 | G92: ¥8–12 | H92: 8 | I92: 10 | J92: 19 | K92: 9 | L92: 30 | M92: 0.83 | N92: 4 | O92: 5.7 | P92: 6.7 | Q92: 5 | R92: 1 | S92: 8 | T92: 9 | U92: =COUNTIF(SKU明细!D3:D607,B92) -> 1 | V92: 需求偏冷：「想要」人数中位数仅 9，自然流量薄弱，靠搜索自然成交难度大，需搭配低价或搭售；价格中等：全新竞品中位价 ¥16，主流带 ¥10–19，薄利走量，需控运损；竞争中等：Top30 中出现 1 个不同品牌，需要在主图和标题上做出差异；售后可控：常规小家电，做好成色描述与功能实测视频即可；无资质门槛：上架无特殊资质要求，标题可自由发挥；耗材属性强：可与主机绑定做「主品+耗材」复购套餐，锁定回头客；该品类样本中未见自有品牌在售，属空白位——无内卷，但也需教育市场成本；新手友好：商品好描述、体积小发货轻、决策快，适合铺量上架 | W92: 谨慎试水：少量上架测款，只有当月出单才补货；写清「瑕疵/为什么低价」
A93: 91 | B93: 便携干衣机 | C93: C | D93: 5.2 | E93: 49 | F93: 42 | G93: ¥41–42 | H93: 39 | I93: 45 | J93: 60 | K93: 3 | L93: 30 | M93: 0.7 | N93: 2.4 | O93: 7.8 | P93: 6.7 | Q93: 1 | R93: 9 | S93: 5 | T93: 4 | U93: =COUNTIF(SKU明细!D3:D607,B93) -> 2 | V93: 需求偏冷：「想要」人数中位数仅 3，自然流量薄弱，靠搜索自然成交难度大，需搭配低价或搭售；单件利润空间可观：全新竞品中位价 ¥49，P25–P75 主流带 ¥45–60，有腾挪定价空间；竞争中等：Top30 中出现 4 个不同品牌，需要在主图和标题上做出差异；售后风险极低：非电器或耗材形态，基本无充电/质保/退货纠纷；⚠️ 合规强监管：属强资质敏感品类，资质/标签/宣称任一不合规即触发下架或扣分；新手门槛偏高：需讲清参数/尺寸/安装或操作说明，图文投入要足 | W93: 谨慎试水：少量上架测款，只有当月出单才补货；写清「瑕疵/为什么低价」
A94: 92 | B94: 立式切菜器 | C94: C | D94: 5.2 | E94: 18 | F94: 14 | G94: ¥12–15 | H94: 11 | I94: 16 | J94: 29 | K94: 3 | L94: 30 | M94: 0.7 | N94: 2.4 | O94: 5.9 | P94: 6.7 | Q94: 3 | R94: 10 | S94: 8 | T94: 6 | U94: =COUNTIF(SKU明细!D3:D607,B94) -> 1 | V94: 需求偏冷：「想要」人数中位数仅 3，自然流量薄弱，靠搜索自然成交难度大，需搭配低价或搭售；价格中等：全新竞品中位价 ¥18，主流带 ¥16–29，薄利走量，需控运损；竞争中等：Top30 中出现 4 个不同品牌，需要在主图和标题上做出差异；售后风险极低：非电器或耗材形态，基本无充电/质保/退货纠纷；⚠️ 合规强监管：属强资质敏感品类，资质/标签/宣称任一不合规即触发下架或扣分；有一定复购：刀头/磨头/袋装等配套件可带动二次成交；该品类样本中未见自有品牌在售，属空白位——无内卷，但也需教育市场成本；新手友好：商品好描述、体积小发货轻、决策快，适合铺量上架 | W94: 谨慎试水：少量上架测款，只有当月出单才补货；写清「瑕疵/为什么低价」
A95: 93 | B95: 智能可视洁牙器 | C95: C | D95: 5.14 | E95: 76 | F95: 38 | G95: ¥31–44 | H95: 29 | I95: 58 | J95: 117 | K95: 4 | L95: 30 | M95: 0.7 | N95: 2.8 | O95: 8.4 | P95: 6.9 | Q95: 4 | R95: 2 | S95: 6 | T95: 4 | U95: =COUNTIF(SKU明细!D3:D607,B95) -> 2 | V95: 需求偏冷：「想要」人数中位数仅 4，自然流量薄弱，靠搜索自然成交难度大，需搭配低价或搭售；单件利润空间可观：全新竞品中位价 ¥76，P25–P75 主流带 ¥58–117，有腾挪定价空间；竞争中等：Top30 中出现 1 个不同品牌，需要在主图和标题上做出差异；售后风险极低：非电器或耗材形态，基本无充电/质保/退货纠纷；无资质门槛：上架无特殊资质要求，标题可自由发挥；该品类样本中未见自有品牌在售，属空白位——无内卷，但也需教育市场成本 | W95: 谨慎试水：少量上架测款，只有当月出单才补货；写清「瑕疵/为什么低价」
A96: 94 | B96: 电动指甲刀 | C96: C | D96: 5.11 | E96: 26 | F96: 16 | G96: ¥13–18 | H96: 12 | I96: 18 | J96: 35 | K96: 4 | L96: 60 | M96: 0.62 | N96: 3.6 | O96: 6.6 | P96: 3.5 | Q96: 2 | R96: 10 | S96: 8 | T96: 6 | U96: =COUNTIF(SKU明细!D3:D607,B96) -> 4 | V96: 需求偏冷：「想要」人数中位数仅 4，自然流量薄弱，靠搜索自然成交难度大，需搭配低价或搭售；价格中等：全新竞品中位价 ¥26，主流带 ¥18–35，薄利走量，需控运损；竞争激烈：Top30 里已挤进 2 个品牌，头部品牌已形成价格锚定，正面硬拼不划算；售后风险极低：非电器或耗材形态，基本无充电/质保/退货纠纷；⚠️ 合规强监管：属强资质敏感品类，资质/标签/宣称任一不合规即触发下架或扣分；有一定复购：刀头/磨头/袋装等配套件可带动二次成交；该品类样本中未见自有品牌在售，属空白位——无内卷，但也需教育市场成本；新手友好：商品好描述、体积小发货轻、决策快，适合铺量上架 | W96: 谨慎试水：少量上架测款，只有当月出单才补货；写清「瑕疵/为什么低价」
A97: 95 | B97: 矫姿带 | C97: C | D97: 5.1 | E97: 20 | F97: 12 | G97: ¥10–15 | H97: 10 | I97: 15 | J97: 28 | K97: 4 | L97: 30 | M97: 0.53 | N97: 2.8 | O97: 6.1 | P97: 7 | Q97: 4 | R97: 6 | S97: 8 | T97: 3 | U97: =COUNTIF(SKU明细!D3:D607,B97) -> 19 | V97: 需求偏冷：「想要」人数中位数仅 4，自然流量薄弱，靠搜索自然成交难度大，需搭配低价或搭售；价格中等：全新竞品中位价 ¥20，主流带 ¥15–28，薄利走量，需控运损；竞争温和：在售 Top30 覆盖 1 个品牌，格局分散，新链接有出头机会；售后风险极低：非电器或耗材形态，基本无充电/质保/退货纠纷；宣称需克制：文案避免「治疗/根治/祛斑」等医疗功效词，用「清洁/护理/辅助」表述；该品类样本中未见自有品牌在售，属空白位——无内卷，但也需教育市场成本；新手友好：商品好描述、体积小发货轻、决策快，适合铺量上架 | W97: 谨慎试水：少量上架测款，只有当月出单才补货；写清「瑕疵/为什么低价」
A98: 96 | B98: 净水器 | C98: C | D98: 5.04 | E98: 35 | F98: 15 | G98: ¥14–16 | H98: 13 | I98: 20 | J98: 39 | K98: 3 | L98: 30 | M98: 0.67 | N98: 2.4 | O98: 6.6 | P98: 6 | Q98: 2 | R98: 6 | S98: 6 | T98: 7 | U98: =COUNTIF(SKU明细!D3:D607,B98) -> 1 | V98: 需求偏冷：「想要」人数中位数仅 3，自然流量薄弱，靠搜索自然成交难度大，需搭配低价或搭售；价格中等：全新竞品中位价 ¥35，主流带 ¥20–39，薄利走量，需控运损；竞争中等：Top30 中出现 8 个不同品牌，需要在主图和标题上做出差异；售后风险极低：非电器或耗材形态，基本无充电/质保/退货纠纷；宣称需克制：文案避免「治疗/根治/祛斑」等医疗功效词，用「清洁/护理/辅助」表述；有一定复购：刀头/磨头/袋装等配套件可带动二次成交；自有品牌在该品类已有零星在售（2 条，占 7%），说明存在成交但尚未形成压倒性优势，适合抢占头部位置 | W98: 谨慎试水：少量上架测款，只有当月出单才补货；写清「瑕疵/为什么低价」
A99: 97 | B99: 毛球修剪器 | C99: C | D99: 4.99 | E99: 16 | F99: 8 | G99: ¥6–9 | H99: 6 | I99: 10 | J99: 20 | K99: 2 | L99: 30 | M99: 0.53 | N99: 1.9 | O99: 5.1 | P99: 6.7 | Q99: 2 | R99: 10 | S99: 9 | T99: 6 | U99: =COUNTIF(SKU明细!D3:D607,B99) -> 7 | V99: 需求偏冷：「想要」人数中位数仅 2，自然流量薄弱，靠搜索自然成交难度大，需搭配低价或搭售；价格中等：全新竞品中位价 ¥16，主流带 ¥10–20，薄利走量，需控运损；竞争中等：Top30 中出现 5 个不同品牌，需要在主图和标题上做出差异；售后风险极低：非电器或耗材形态，基本无充电/质保/退货纠纷；⚠️ 合规强监管：属强资质敏感品类，资质/标签/宣称任一不合规即触发下架或扣分；有一定复购：刀头/磨头/袋装等配套件可带动二次成交；该品类样本中未见自有品牌在售，属空白位——无内卷，但也需教育市场成本；新手友好：商品好描述、体积小发货轻、决策快，适合铺量上架 | W99: 谨慎试水：少量上架测款，只有当月出单才补货；写清「瑕疵/为什么低价」
A100: 98 | B100: 家禽拔毛器 | C100: C | D100: 4.89 | E100: 35 | F100: 20 | G100: ¥15–24 | H100: 14 | I100: 20 | J100: 39 | K100: 2 | L100: 60 | M100: 0.7 | N100: 2.7 | O100: 6.8 | P100: 3.8 | Q100: 3 | R100: 10 | S100: 8 | T100: 4 | U100: =COUNTIF(SKU明细!D3:D607,B100) -> 1 | V100: 需求偏冷：「想要」人数中位数仅 2，自然流量薄弱，靠搜索自然成交难度大，需搭配低价或搭售；价格中等：全新竞品中位价 ¥35，主流带 ¥20–39，薄利走量，需控运损；竞争激烈：Top30 里已挤进 1 个品牌，头部品牌已形成价格锚定，正面硬拼不划算；售后风险极低：非电器或耗材形态，基本无充电/质保/退货纠纷；⚠️ 合规强监管：属强资质敏感品类，资质/标签/宣称任一不合规即触发下架或扣分；该品类样本中未见自有品牌在售，属空白位——无内卷，但也需教育市场成本；新手友好：商品好描述、体积小发货轻、决策快，适合铺量上架 | W100: 谨慎试水：少量上架测款，只有当月出单才补货；写清「瑕疵/为什么低价」
...

Sheet SKU明细
A1: SKU 级选品清单（按评级与评分排序；建议售价=单件挂价起点，最低可接受价=含运费不亏的保本红线）
A2: 序号 | B2: 品牌 | C2: 评级 | D2: 品类 | E2: 产品名称 | F2: 商品名称 | G2: 商品编码 | H2: 建议售价 | I2: 建议区间 | J2: 最低可接受价 | K2: 竞品中位价 | L2: 想要中位 | M2: 综合评分 | N2: 行动建议
A3: 1 | B3: mericle | C3: S | D3: 剃须刀刀头 | E3: 刀头 | F3: 剃须刀/刀头（塑封） | G3: TXD-04 | H3: 12 | I3: ¥9–15 | J3: 8 | K3: 15 | L3: 113 | M3: 8.17 | N3: 全员力推，首批打满库存；标题带「全新未拆封+实拍」，主图放品牌背书
A4: 2 | B4: mericle | C4: S | D4: 剃须刀刀头 | E4: mericle便携式剃须刀/刀头 | F4: M/迷你剃须刀/二代/刀头 | G4: TXD-38 | H4: 12 | I4: ¥9–15 | J4: 8 | K4: 15 | L4: 113 | M4: 8.17 | N4: 全员力推，首批打满库存；标题带「全新未拆封+实拍」，主图放品牌背书
A5: 3 | B5: mericle | C5: S | D5: 剃须刀刀头 | E5: mericle鼻毛修剪器刀头 | F5: 美丽蔻BMXJQ 刀头 | G5: Mericle-bmxjq001 | H5: 12 | I5: ¥9–15 | J5: 8 | K5: 15 | L5: 113 | M5: 8.17 | N5: 全员力推，首批打满库存；标题带「全新未拆封+实拍」，主图放品牌背书
A6: 4 | B6: mericle | C6: S | D6: 剃须刀刀头 | E6: mericle鼻毛修剪器刀头 | F6: Mericle/BMXJQ/黑色/刀头 | G6: Mericle/BMXJQ/DT | H6: 12 | I6: ¥9–15 | J6: 8 | K6: 15 | L6: 113 | M6: 8.17 | N6: 全员力推，首批打满库存；标题带「全新未拆封+实拍」，主图放品牌背书
A7: 5 | B7: mericle | C7: S | D7: 剃须刀刀头 | E7: mericle鼻毛修剪器刀头 | F7: Mericle/BMXJQ/二代刀头 | G7: Mericle/BMXJQ/002 | H7: 12 | I7: ¥9–15 | J7: 8 | K7: 15 | L7: 113 | M7: 8.17 | N7: 全员力推，首批打满库存；标题带「全新未拆封+实拍」，主图放品牌背书
A8: 6 | B8: mericle | C8: S | D8: 剃须刀刀头 | E8: 康佳鼻毛修剪器刀头 | F8: 康佳/BMXJQ/二代/刀头 | G8: BMXJQ-07 | H8: 12 | I8: ¥9–15 | J8: 8 | K8: 15 | L8: 113 | M8: 8.17 | N8: 全员力推，首批打满库存；标题带「全新未拆封+实拍」，主图放品牌背书
A9: 7 | B9: mericle | C9: S | D9: 剃须刀刀头 | E9: mericle鼻毛修剪器刀头 | F9: M/BMXJQ/五代/刀头 | G9: BMXJQ-16 | H9: 12 | I9: ¥9–15 | J9: 8 | K9: 15 | L9: 113 | M9: 8.17 | N9: 全员力推，首批打满库存；标题带「全新未拆封+实拍」，主图放品牌背书
A10: 8 | B10: mericle | C10: S | D10: 剃须刀刀头 | E10: 剃须刀刀头 | F10: Mericle/透明双头剃须刀/刀头 | G10: TXD-92 | H10: 12 | I10: ¥9–15 | J10: 8 | K10: 15 | L10: 113 | M10: 8.17 | N10: 全员力推，首批打满库存；标题带「全新未拆封+实拍」，主图放品牌背书
A11: 9 | B11: mericle | C11: S | D11: 剃须刀刀头 | E11: 刀头 | F11: 多功能剃须刀YC-808/刀头 | G11: TXD-138 | H11: 12 | I11: ¥9–15 | J11: 8 | K11: 15 | L11: 113 | M11: 8.17 | N11: 全员力推，首批打满库存；标题带「全新未拆封+实拍」，主图放品牌背书
A12: 10 | B12: mericle | C12: S | D12: 剃须刀刀头 | E12: 毛球修剪器刀头 | F12: Mericle/毛球修剪器01/刀头 | G12: MQXJQ-11 | H12: 12 | I12: ¥9–15 | J12: 8 | K12: 15 | L12: 113 | M12: 8.17 | N12: 全员力推，首批打满库存；标题带「全新未拆封+实拍」，主图放品牌背书
A13: 11 | B13: mericle | C13: S | D13: 剃须刀刀头 | E13: 手动刮胡刀刀头 | F13: Mericle/手动剃须刀/MSD-001/刀头 | G13: TXD-123 | H13: 12 | I13: ¥9–15 | J13: 8 | K13: 15 | L13: 113 | M13: 8.17 | N13: 全员力推，首批打满库存；标题带「全新未拆封+实拍」，主图放品牌背书
A14: 12 | B14: 康佳 | C14: S | D14: 剃须刀刀头 | E14: 康佳便携式剃须刀刀头 | F14: 剃须刀/刀头（塑封） | G14: TXD-04 | H14: 12 | I14: ¥9–15 | J14: 8 | K14: 15 | L14: 113 | M14: 8.17 | N14: 全员力推，首批打满库存；标题带「全新未拆封+实拍」，主图放品牌背书
... A436: 434 | B436: mericle | C436: B | D436: 黑头仪 | E436: 黑头仪 | F436: Mericle/小气泡黑头仪/X19（Z） | G436: Mericle-HTY-03 | H436: 22 | I436: ¥17–27 | J436: 16 | K436: 36 | L436: 2.5 | M436: 5.55 | N436: 常规备选，放在长尾分类；用低价冲量，不单独投流
A437: 435 | B437: mericle | C437: B | D437: 黑头仪 | E437: 黑头仪 | F437: Mericle/小气泡黑头仪/XQP003（新款） | H437: 22 | I437: ¥17–27 | J437: 16 | K437: 36 | L437: 2.5 | M437: 5.55 | N437: 常规备选，放在长尾分类；用低价冲量，不单独投流
A438: 436 | B438: 美悟 | C438: B | D438: 黑头仪 | E438: 美悟微晶吸黑头仪 | F438: 美悟 黑头仪（充电款） 美悟 黑头仪（充电款） | G438: MY-HTC MY-HTD | H438: 22 | I438: ¥17–27 | J438: 16 | K438: 36 | L438: 2.5 | M438: 5.55 | N438: 常规备选，放在长尾分类；用低价冲量，不单独投流
A439: 437 | B439: 通货 | C439: B | D439: 洗眼液 | E439: 洗眼液 | F439: 洗眼液/260ml | G439: XYY-01 | H439: 12 | I439: ¥10–13 | J439: 10 | K439: 18 | L439: 18.5 | M439: 5.54 | N439: 常规备选，放在长尾分类；用低价冲量，不单独投流
A440: 438 | B440: mericle | C440: B | D440: 鼻毛修剪器 | E440: mericle鼻毛修剪器 | F440: 美丽蔻BMXJQ充电款 | G440: Mericle-bmxjqC | H440: 12 | I440: ¥10–15 | J440: 10 | K440: 15 | L440: 2 | M440: 5.49 | N440: 常规备选，放在长尾分类；用低价冲量，不单独投流
A441: 439 | B441: mericle | C441: B | D441: 鼻毛修剪器 | E441: mericle鼻毛修剪器 | F441: Mericle/BMXJQ/黑色 | G441: Mericle/BMXJQ/HS | H441: 12 | I441: ¥10–15 | J441: 10 | K441: 15 | L441: 2 | M441: 5.49 | N441: 常规备选，放在长尾分类；用低价冲量，不单独投流
A442: 440 | B442: mericle | C442: B | D442: 鼻毛修剪器 | E442: mericle鼻毛修剪器 | F442: Mericle/BMXJQ/二代 | G442: M/BMXJQ/0310 | H442: 12 | I442: ¥10–15 | J442: 10 | K442: 15 | L442: 2 | M442: 5.49 | N442: 常规备选，放在长尾分类；用低价冲量，不单独投流
A443: 441 | B443: mericle | C443: B | D443: 鼻毛修剪器 | E443: mericle鼻毛修剪器 | F443: Mericle/BMXJQ/三代 | G443: BMXJQ-12 | H443: 12 | I443: ¥10–15 | J443: 10 | K443: 15 | L443: 2 | M443: 5.49 | N443: 常规备选，放在长尾分类；用低价冲量，不单独投流
A444: 442 | B444: mericle | C444: B | D444: 鼻毛修剪器 | E444: mericle鼻毛修剪器 | F444: M/BMXJQ/五代/橙色/BMQ-003 | G444: BMXJQ-14 | H444: 12 | I444: ¥10–15 | J444: 10 | K444: 15 | L444: 2 | M444: 5.49 | N444: 常规备选，放在长尾分类；用低价冲量，不单独投流
A445: 443 | B445: mericle | C445: B | D445: 鼻毛修剪器 | E445: mericle鼻毛修剪器 | F445: M/BMXJQ/五代/蓝色/BMQ-003 | G445: BMXJQ-15 | H445: 12 | I445: ¥10–15 | J445: 10 | K445: 15 | L445: 2 | M445: 5.49 | N445: 常规备选，放在长尾分类；用低价冲量，不单独投流
A446: 444 | B446: mericle | C446: B | D446: 鼻毛修剪器 | E446: mericle鼻毛修剪器 | F446: M/BMXJQ/五代/黑色/BMQ-003 | G446: BMXJQ-42 | H446: 12 | I446: ¥10–15 | J446: 10 | K446: 15 | L446: 2 | M446: 5.49 | N446: 常规备选，放在长尾分类；用低价冲量，不单独投流
A447: 445 | B447: mericle | C447: B | D447: 鼻毛修剪器 | E447: mericle鼻毛修剪器 | F447: Mericle/BMXJQ/七代/蓝色 | G447: BMXJQ-21 | H447: 12 | I447: ¥10–15 | J447: 10 | K447: 15 | L447: 2 | M447: 5.49 | N447: 常规备选，放在长尾分类；用低价冲量，不单独投流
A448: 446 | B448: mericle | C448: B | D448: 鼻毛修剪器 | E448: mericle鼻毛修剪器 | F448: Mericle/BMXJQ/七代/黑色 | G448: BMXJQ-22 | H448: 12 | I448: ¥10–15 | J448: 10 | K448: 15 | L448: 2 | M448: 5.49 | N448: 常规备选，放在长尾分类；用低价冲量，不单独投流
A449: 447 | B449: mericle | C449: B | D449: 鼻毛修剪器 | E449: 鼻毛修剪器 | F449: Mericle /电动BMXJQ升级款/蓝色 | G449: BMXJQ-35 | H449: 12 | I449: ¥10–15 | J449: 10 | K449: 15 | L449: 2 | M449: 5.49 | N449: 常规备选，放在长尾分类；用低价冲量，不单独投流
... A607: 605 | B607: 康佳 | C607: D | D607: 配件周边 | E607: / | F607: 透明罐 | G607: TMG-01 | H607: 20 | I607: ¥16–23 | J607: 15 | K607: 37 | L607: 13 | M607: 6.85 | N607: 不建议投入：合规/售后/需求三重风险，优先出库存或转做搭售赠品

Sheet 品牌品类矩阵
A1: 品牌 × 品类供给矩阵（数字=该品牌该品类 SKU 数，空白=无货，可作差异化选品方向）
A2: 品类 | B2: 评级 | C2: mericle | D2: 夏新 | E2: 奥克斯 | F2: 康佳 | G2: 现代 | H2: 美悟 | I2: 通货 | J2: 合计 | K2: 建议售价
A3: 便携迷你剃须刀 | B3: B | C3: 20 | D3: 23 | E3: 2 | F3: 45 | G3: 1 | H3: 0 | I3: 0 | J3: =SUM(C3:I3) -> 91
A4: 鼻毛修剪器 | B4: B | C4: 15 | D4: 1 | E4: 0 | F4: 23 | G4: 3 | H4: 1 | I4: 0 | J4: =SUM(C4:I4) -> 43
A5: 电动剃须刀 | B5: B | C5: 15 | D5: 4 | E5: 0 | F5: 7 | G5: 0 | H5: 2 | I5: 3 | J5: =SUM(C5:I5) -> 31
A6: 电动剃毛器 | B6: C | C6: 15 | D6: 0 | E6: 0 | F6: 13 | G6: 0 | H6: 0 | I6: 0 | J6: =SUM(C6:I6) -> 28
A7: 理发器 | B7: B | C7: 3 | D7: 0 | E7: 0 | F7: 21 | G7: 0 | H7: 0 | I7: 2 | J7: =SUM(C7:I7) -> 26
A8: 电动磨脚器 | B8: B | C8: 10 | D8: 3 | E8: 0 | F8: 8 | G8: 0 | H8: 3 | I8: 1 | J8: =SUM(C8:I8) -> 25
A9: 直发梳 | B9: B | C9: 15 | D9: 0 | E9: 0 | F9: 8 | G9: 0 | H9: 1 | I9: 1 | J9: =SUM(C9:I9) -> 25
A10: 剃须刀刀头 | B10: S | C10: 11 | D10: 3 | E10: 0 | F10: 8 | G10: 1 | H10: 0 | I10: 0 | J10: =SUM(C10:I10) -> 23
A11: 矫姿带 | B11: C | C11: 19 | D11: 0 | E11: 0 | F11: 0 | G11: 0 | H11: 0 | I11: 0 | J11: =SUM(C11:I11) -> 19
A12: 电动牙刷 | B12: B | C12: 1 | D12: 0 | E12: 0 | F12: 7 | G12: 0 | H12: 7 | I12: 0 | J12: =SUM(C12:I12) -> 15
A13: 电动睫毛卷 | B13: B | C13: 9 | D13: 0 | E13: 0 | F13: 0 | G13: 0 | H13: 5 | I13: 0 | J13: =SUM(C13:I13) -> 14
A14: 车载吸尘器 | B14: B | C14: 11 | D14: 0 | E14: 0 | F14: 0 | G14: 1 | H14: 2 | I14: 0 | J14: =SUM(C14:I14) -> 14
... A94: 隐形眼镜清洁盒 | B94: B | C94: 1 | D94: 0 | E94: 0 | F94: 0 | G94: 0 | H94: 0 | I94: 0 | J94: =SUM(C94:I94) -> 1
A95: 合计 | C95: =SUM(C3:C94) -> 279 | D95: =SUM(D3:D94) -> 64 | E95: =SUM(E3:E94) -> 2 | F95: =SUM(F3:F94) -> 162 | G95: =SUM(G3:G94) -> 19 | H95: =SUM(H3:H94) -> 42 | I95: =SUM(I3:I94) -> 37 | J95: =SUM(J3:J94) -> 605

Sheet 定价与上架策略
A1: 定价与上架策略手册
A3: 一、定价原则
A4: 竞品锚定 | B4: 建议售价基于闲鱼在售竞品价格分位测算；优先取「全新未拆封」子集的中位价（本表货源为全新货），避开二手折价干扰。
A5: 分位取值 | B5: S/A 级取 P25–P50 主流走量带；B/C 级取 P10–P25 低价冲量带；D 级仅求快速回笼资金。
A6: 保本红线 | B6: 最低可接受价 = P10 × 0.95。低于此价上架即亏，需核对进货成本后决定是否放弃。
A7: 成本核算 | B7: 净利 = 建议售价 − 进货成本 − 运费 − 平台费。净利低于 ¥8 的 SKU 建议直接放弃。
A8: 通货提示 | B8: 本表多为通货/白牌，定价务必低于同款品牌旗舰；用「批量清仓/尾货/公司福利」解释低价，转化率明显更高。
A10: 二、标题与主图
A11: 标题公式 | B11: 品牌 + 品类 + 核心参数 + 「全新未拆封」+ 「实拍」。例：康佳 便携式剃须刀 双刀头防水Type-C充电 全新未拆封 实拍
A12: 主图三张 | B12: ①实物实拍（非官方图）②开箱/功能演示 ③尺寸对比图
A13: 搜索词 | B13: 标题覆盖用户真实搜索词：品类词 + 属性词（便携/防水/无线/迷你）+ 场景词（学生/差旅/送礼）。
A15: 三、上架与售后风控
A16: 电器必拍 | B16: 电器类上架前拍 15 秒开箱视频存档，可大幅降低退货纠纷与「描述不符」投诉。
A17: 成色描述 | B17: 如实写明功能状态、有无划痕、是否拆封；低价商品尤其要写清「为什么低价」。
A18: 耗材组合 | B18: 刀头/磨头/袋装/口罩等耗材单独建合集链接，与主机打包做「主品+耗材」组合价，锁定复购。
A19: 合规红线 | B19: 洗眼液/明目护眼液/漱口水/芦荟胶/强脉冲光/脱毛仪等强监管品类，个人商家不建议上架；标题禁用「治疗/根治/祛斑/杀菌」等词。
A21: 四、节奏建议
A22: 首批上架 | B22: 先上 S+A 级品类全部 SKU（建议 30–60 个链接），跑通自然流量后再扩。
A23: 测款节奏 | B23: 上架后 7 天内出单即补货并加投；满 14 天零出单则降价一档或下架换品。
A24: 季节备货 | B24: 夏季备风扇/挂腰风扇/防晒口罩/驱蚊手环；冬季备毛球修剪器/烘鞋器/保暖口罩/暖菜板；春季备修足器/除螨仪。
A25: 复购运营 | B25: 耗材类主品成交后 15 天内推送耗材复购提醒，耗材毛利率通常高于主品。
